Workbook

Sheet README
A1: NanoVox — Corpus v9 Build Bible
A2: 600 calls · 12 weeks · Mon 6 Jul – Fri 25 Sep 2026 · 95 employers sized to ChoiceBuilder's real 2–500 band · 122 verified rules
A4: What this is | B4: The single reference for building the NanoVox corpus and the intelligence layer on top of it. The analytical framework is unchanged from v8 — data model, tag schema, outcomes, escalation logic, quality framework, metrics, intelligence register and the three rule layers all carry over intact. What changed is the sample: 600 calls instead of 360, and a group-size distribution rebuilt to match the population ChoiceBuilder actually serves.
A5: Why 600 and not 360 | B5: 360 was sized against the v7 framework. v8 added five dimensions that each multiply the number of cells needing a denominator — touchpoint, escalation trigger_type, rule_id, control exception type and process_gap. Working backwards from the tightest of those, knowledge failure by rule_id needed about 620 calls to put the top rule above fifteen, control exceptions by type about 640, self-inflicted demand by component about 470, and the consecutive-window account risk test about 600. 600 clears all of them bar the last few escalation trigger types, which are reported as counts rather than rates by design.
A6: Why group size had to be rebuilt | B6: ChoiceBuilder serves groups of 2–500 eligible employees, and the published book is roughly 10,000 groups to 140,000 members — an average near 14. The v8 sample averaged 70 lives a group, which is not that population. Size is not cosmetic here: it decides which rules apply. Below 20 eligible a group is under Cal-COBRA and ChoiceBuilder sends the election notice; at 20 and above it is federal COBRA and the duty is solely the employer's. The administration fee steps at 8, 20 and 199. Voluntary dental minimums differ for 2–9 against 10–500 groups. Orthodontia availability is gated at 5, 10 and 25 eligible. A corpus without small groups cannot exercise any of it.
A7: The size distribution | B7: 95 employers: 22 in the 2–8 band, 24 in 9–20, 38 in 21–199 and 11 at 200 and above. That puts 46 groups under the federal COBRA threshold and 49 at or above it, so both regimes are live. Because the corpus is call-weighted rather than group-weighted, larger groups are over-represented relative to the book — that is correct, since groups with more members generate more calls, but it is stated here so nobody reads the sample as the book.
A8: Participation is modelled, not assumed | B8: Enrolled lives are derived from eligible employees and a participation rate that depends on whether dental is employer-sponsored or voluntary, and the Employer Master flags every group at or below its applicable threshold. Several groups are deliberately placed below 70% on employer-sponsored dental, and several voluntary groups sit below the enrolled-headcount minimums, so the non-renewal scenarios in the register are real rather than illustrative.
A9: The one modelling rule | B9: A member belongs to an employer. An employer has exactly one broker of record. The member record never carries a broker field — attribution is inherited through the employer, so a broker of record change is corrected in one place and every historical call follows.
A10: Control totals | B10: Weekly Volume, Employer Master, Product & Carrier, Agent Roster and Distribution Targets must each sum to 600. Member Master must sum to 390 member calls and Employer Contacts to 210. Each sheet carries its own check row. A variance means the design is internally inconsistent and transcript writing should stop.
A11: What 600 still will not support | B11: Per-broker complaint rates as precise multiples — a three-group broker carries ten attributed calls, which names a list credibly but does not support '8.5 times the median' as a spoken number. Weekly sub-category claims — fifty calls a week still makes last week's unresolved billing calls about seven. And escalation trigger types five through eight, which are named with explicit counts and never quoted as rates.
A12: Out of scope, deliberately | B12: No broker-initiated calls. No finance or commission queue. No email. The single-source question — that this platform infers everything from conversations and cannot see a silent account — is parked by decision, not by oversight.
A13: Still open | B13: Three items need CHOICE, on the Corrections & Sources sheet: the life guaranteed issue amount, the carrier mix by member, and whether monthly full-roster reconciliation exists at all.
A15: CORPUS CALIBRATION AT 600
A16: Outcome mix: resolved 368, partially resolved 73, escalated 34, unresolved 125. Resolved lands at 61% against a 62% target — close to a real call-centre mix, by design of the final 150.
A17: Product mix runs slightly harder than real volume: program-level 83 against a target of 67 (early batches over-weighted group-level billing and enrolment calls), which leaves dental 263, vision 129 and chiro 52 a little under target.
A18: Root cause: 266 of 600 calls (44%) trace to a Choice-owned or Choice-system root cause.
A19: Treat the corpus as slightly harder than a real call centre on signal density; the outcome mix itself is realistic.
A20: Open items that need CHOICE before any real-data run: life guaranteed-issue amount; carrier mix by member; whether a monthly full-roster reconciliation exists.

Sheet Data Model
A1: Data model
A2: Eight entities and the keys that join them. The important decision recorded here is that broker is a property of the employer and never of the member — a member inherits their broker through their group, so when a broker of record changes there is exactly one row to correct and every historical call re-attributes automatically. The second decision is that signals and rubric markers are separate entities rather than columns on the call, because one call can raise several of each and because a refused marker must remain visible for the score to be auditable. Read this before the Call Tag Schema; the schema describes what gets written, this describes where it lives.
A4: Entity | B4: Primary key | C4: Foreign keys | D4: Cardinality | E4: Fields held here | F4: Why it lives here
A5: Broker | B5: BRK-nn | C5: — | D5: 1 broker → many employers | E5: Agency name, groups in book, lives in book, region, appointment date | F5: Book size must come from Choice's broker records, never from call counts. Deriving it from calls makes the rate self-referential.
A6: Employer | B6: EMP-nnnn | C6: BRK-nn (broker of record) | D6: 1 employer → many members; 1 employer → 1–3 contacts | E6: Legal name, industry, SIC, enrolled lives, region, renewal month, lines held, effective date, premium | F6: The join point for everything. Industry, size and renewal month are never spoken on a call, so they must be reference data.
A7: Member | B7: CB-nnnnnnn | C7: EMP-nnnn | D7: 1 member → many calls | E7: Name, DOB, lines enrolled, effective date, dependents, home zip | F7: Broker is deliberately absent. Inherit it through the employer so a broker of record change corrects in one place.
A8: Employer contact | B8: CON-nnn | C8: EMP-nnnn | D8: 1 contact → many calls | E8: Name, role, authority level (can bind / cannot bind) | F8: Employer calls come from an HR or finance person, not from the group itself. Authority level decides what an agent may action.
A9: Agent | B9: AGT-nn | C9: — | D9: 1 agent → many calls | E9: Name, band, hire date, queue | F9: Score is a property of agent and call. It never rolls up to an account.
A10: Call | B10: C-nnnn | C10: CB / CON, EMP, BRK (derived), AGT | D10: 1 call → many tags; 1 call → many signals | E10: Timestamp, duration, queue, outcome, category, product lines, quality score, transcript | F10: The fact table. Every metric in this workbook is an aggregation over this one entity.
A11: Signal | B11: SIG-nnnn | C11: C-nnnn | D11: many signals → 1 call | E11: Signal type, severity, owner, evidence turn reference | F11: Separate from the call so one call can raise several, and so signal density counts distinct types rather than occurrences.
A12: Rubric marker | B12: MRK-nnnnn | C12: C-nnnn | D12: many markers → 1 call | E12: Dimension, polarity, magnitude, quoted evidence, verification status | F12: Kept at marker level so a refused marker is visible. A score with no marker trail is not auditable.
A14: Join path for broker attribution | B14: Call → Member → Employer → Broker. For employer calls: Call → Contact → Employer → Broker. A broker is only counted in a metric when named aloud in the transcript; the inherited link supplies identity, the transcript supplies the evidence. Where the broker named aloud does not match the employer's broker of record, that mismatch is itself a finding — either the member is confused or the record is stale.

Sheet Call Tag Schema
A1: Call tag schema — 20 fields
A2: Sixteen fields the pipeline must emit for every call. This is the contract between the analysis pipeline and everything downstream: every metric, every signal and every intelligence claim in this workbook is an aggregation over these sixteen fields and nothing else. If a new insight needs data that is not here, the schema changes first and the insight second. Two fields are new in v8 — process_gap, which captures an improvement proposal raised inside a call and gives it a lifecycle so it cannot die as a note, and touchpoint, which records where in the member journey the failure actually originated rather than where it surfaced.
A4: # | B4: Tag | C4: Type | D4: Allowed values | E4: Emitted by | F4: Notes for development
A5: 1 | B5: outcome | C5: enum | D5: RESOLVED · PARTIALLY_RESOLVED · ESCALATED · UNRESOLVED | E5: L2 | F5: Single-valued. Drives FCR, repeat and escalation metrics.
A6: 2 | B6: category | C6: enum | D6: Coverage & Benefits · Claims & EOB · Provider Network · Billing & Premium · Enrollment & ID Cards · Life & Beneficiary · Broker Conduct | E6: L2 | F6: Single-valued. Pharmacy removed — ChoiceBuilder has no pharmacy line. Life & Beneficiary added.
A7: 3 | B7: product_lines | C7: array | D7: dental · vision · life · chiro · program | E7: L2 | F7: Multi-valued. Shares exceed 100%; contact rate uses a single primary line to avoid double counting.
A8: 4 | B8: complaint | C8: object | D8: {present: bool, attributed_to: CHOICE | BROKER | CARRIER | PROVIDER} | E8: L2 | F8: Attribution is mandatory when present. An unattributed complaint total overstates CHOICE's own failure rate.
A9: 5 | B9: signals | C9: array | D9: see Signal Taxonomy sheet | E9: L4 | F9: Zero or more. Distinct types, deduplicated per call.
A10: 6 | B10: escalation | C10: object | D10: {triggered: bool, trigger_type, requested_by_caller: bool, handled: bool} | E10: L2/L4 | F10: triggered is the denominator for escalation integrity. Never use total calls.
A11: 7 | B11: control_exceptions | C11: array | D11: no_recording_disclosure · disclosure_before_verification · missing_benefit_disclosure | E11: L1/L3 | F11: Deterministic checks on the opening turns. The strongest case for real-time assist — a greeting check needs no model.
A12: 8 | B12: knowledge_failure | C12: object | D12: {present: bool, rule_id, correct_statement} | E12: L3 | F12: Must cite a rule ID from the Product Rules sheet. Naming the rule points at one article; naming the agent fixes nothing.
A13: 9 | B13: intent | C13: array | D13: expansion · market_test · cancellation · none | E13: L2 | F13: Verbatim statements only, with the turn reference. Inferred intent is an opinion and will be treated as one.
A14: 10 | B14: quality_score | C14: integer | D14: 0–100 | E14: L3 | F14: Property of the call and the agent. Never averaged to employer, product line or broker.
A15: 11 | B15: markers | C15: array | D15: {dimension, polarity, magnitude, quote, turn_ref, verified} | E15: L3 | F15: Retained at marker level including refused markers, so the score is auditable and the tenet views derive from here.
A16: 12 | B16: aht_seconds | C16: integer | D16: — | E16: telephony | F16: Talk time only. Excludes hold and after-call work — every time-based metric is a floor.
... A24: 20 | B24: impact_scope | C24: string | D24: 1 member · 1 group · N employees · N members + dependents | E24: L2 | F24: NEW. How many people the caller says are affected. This is what turns an individual incident into a group-level one — 'eleven of my people cannot find a provider' is a different finding from one member who cannot.

Sheet Outcomes
A1: Call outcomes — definitions and worked examples
A2: Four outcome values, and the distinctions between them decide a large share of the platform's numbers — first-contact resolution, the failure-driven repeat rate, escalation integrity and self-inflicted demand all key off this single field. The test that separates them is not whether the caller was satisfied and not whether the agent performed well; it is whether an owned, committed action remains open at the moment the call disconnects, and who owns it. A call can be handled beautifully and still be UNRESOLVED. A caller can be perfectly content and the call still ESCALATED. Read the decision test in order — it resolves almost every edge case.
A4: Outcome | B4: Definition | C4: The test | D4: Worked example from the corpus | E4: What it is NOT | F4: Edge cases | G4: Effect on metrics
A5: RESOLVED | B5: The caller's issue was concluded during the call. Nothing further is required from the caller, the agent, Choice, a carrier or a broker. | C5: At disconnect, is there any open action owned by anyone? If no, RESOLVED. | D5: C-0001 — a member's crown claim was denied. The agent explained both waiting periods, confirmed the eligibility date, advised on sequencing the second crown, and sent a written summary. Nothing is outstanding. | E5: Not 'the caller was satisfied'. Not 'the agent gave correct information'. Correct information that leaves the caller unable to act is UNRESOLVED. | F5: An agent who delivers bad news correctly and completely, with nothing left open, is RESOLVED even if the caller is unhappy. A written summary sent during the call does not create an open action. | G5: The only value counted in the FCR numerator, and then only if no related contact follows within 14 days.
A6: PARTIALLY RESOLVED | B6: Part of the issue was concluded and part remains open, with a named action and an owner inside Choice or a carrier. | C6: Was at least one substantive question answered, AND does at least one committed action remain with a named owner and a timeframe? If both, PARTIALLY RESOLVED. | D6: C-0002 — an employer's chiropractic network gap. The agent confirmed the limitation, ruled out the two remedies the employer wanted, and committed to a network density report from Landmark within a week plus a written explanation for the affected employees that day. | E6: Not a soft version of UNRESOLVED. If nothing was answered and nothing was committed, it is UNRESOLVED. | F6: A dependency on a third party such as a carrier is PARTIALLY RESOLVED, not ESCALATED — escalation means ownership moved inside the organisation to someone with authority the agent lacks. A vague 'I'll look into it' with no owner, reference or date is UNRESOLVED. | G6: Sits in the FCR denominator, never the numerator. Counts toward open-action ageing.
A7: ESCALATED | B7: Ownership of the issue was transferred to a named party with authority the agent does not have, with a reference, and the work continues after the call ends. | C7: Is there a named owner outside the agent's authority, a reference number, and a committed timeframe? All three, or it is not escalated. | D7: C-0005 — an employer billed for fourteen leavers over six cycles after a broker told them email notification was sufficient. The agent raised a reconciliation, escalated the broker conduct to a named owner in Broker Relations the same day, and gave two references. | E7: NOT a live transfer to another agent. NOT a promise to 'pass it on'. NOT a note on the account. A transfer to a peer who could have handled it anyway is not escalation, it is routing. | F7: Escalation may be agent-initiated as well as caller-requested; both count. An escalation with no reference given to the caller is tagged ESCALATED but flagged, because the caller has no way to chase it. Escalating something inside the agent's own authority is over-escalation — see Escalation Logic. | G7: The numerator of escalation integrity. Sits in the FCR denominator, never the numerator.
A8: UNRESOLVED | B8: The caller's issue is materially unchanged and no owned action exists. | C8: At disconnect, is the caller in the same position they were in when they rang, with nothing committed by anyone? If yes, UNRESOLVED. | D8: C-0004 — a member chasing a dental ID card. The agent was polite and procedurally correct, never established where the card had been sent, offered the portal, and closed. The member still has no card and an appointment on Friday. | E8: Not 'the agent was rude'. Most unresolved calls in this corpus are polite. Not 'the answer was no' — a correct, complete no with nothing outstanding is RESOLVED. | F8: The 'correct but useless' call is the important edge: the agent states a rule accurately and the caller still cannot act, with no route offered. That is UNRESOLVED. An explicit escalation request that is refused with no alternative is almost always UNRESOLVED and additionally raises escalation_missed. | G8: The denominator of the failure-driven repeat rate. Feeds self-inflicted demand when a second contact follows.
A10: Decision order | B10: 1. Did ownership move to someone with authority the agent lacks, with a reference and a date? → ESCALATED. 2. Otherwise, is any committed action with a named owner still open? → PARTIALLY RESOLVED. 3. Otherwise, is the caller's issue concluded? → RESOLVED. 4. Otherwise → UNRESOLVED. Apply in this order. Satisfaction, tone and agent score play no part in it.

Sheet Escalation Logic
A1: Escalation — triggered, handled, and how they relate to outcome
A2: escalation.triggered and outcome are two different fields answering two different questions, and conflating them is the single most common way an escalation metric becomes meaningless. TRIGGERED asks whether the call contained a condition that warranted escalation — a fact about the situation, detectable from the transcript, independent of what the agent did. HANDLED asks whether it was actually routed. OUTCOME records where the call ended. Escalation integrity is measured as handled divided by triggered, never as escalations divided by all calls: against all calls a rate of zero reads as good news, whereas against warranted calls it reads as a control failure, which is what it is.
A4: Field | B4: What it answers | C4: Who or what determines it | D4: Why it is separate
A5: escalation.triggered | B5: Did this call contain a condition that warranted escalation? | C5: The situation, detected from the transcript against the trigger list below. Deterministic where possible. | D5: It is the denominator. It must be independent of the agent's behaviour, or a poor agent shrinks their own denominator and scores well.
A6: escalation.requested_by_caller | B6: Did the caller explicitly ask for a supervisor or someone senior? | C6: The caller's words, verbatim, with a turn reference. | D6: The most defensible subset of triggers — no interpretation involved. A good first proof that the evidence model works.
A7: escalation.handled | B7: Was ownership actually transferred to a named party with a reference? | C7: The agent's actions. | D7: It is the numerator.
A8: escalation.trigger_type | B8: Which condition fired. | C8: The trigger list below. | D8: Lets Broker Relations, Compliance and Account Management each see only their own escalations.
A9: outcome | B9: Where did the call end? | C9: The Outcomes sheet decision order. | D9: A call can be triggered and handled and still end PARTIALLY RESOLVED if the escalation covers only part of the issue.
A11: THE MATRIX
A12: Combination | B12: Resulting outcome | C12: What it means | D12: Example | E12: Note
A13: TRIGGERED = true · HANDLED = true | B13: ESCALATED | C13: Correct handling. Counts in both numerator and denominator of escalation integrity. | D13: C-0005 — broker conduct routed to a named owner in Broker Relations the same day with a reference. | E13: None. This is the target state.
A14: TRIGGERED = true · HANDLED = false | B14: Usually UNRESOLVED; occasionally PARTIALLY RESOLVED | C14: The failure case. Counts in the denominator only, and raises signal escalation_missed. This is the refusal rate. | D14: C-0010 — a CFO states he is going out to bid, asks twice for someone senior, and is offered a note on the account. | E14: The most expensive miss in the corpus. In the design, 25 of 43 triggered calls land here — a 58% refusal rate.
A15: TRIGGERED = false · HANDLED = true | B15: ESCALATED, flagged | C15: Over-escalation. The agent routed something inside their own authority. | D15: An agent sending a straightforward billing credit to a supervisor rather than raising it themselves. | E15: Not a quality win. It is a cost and a capability signal — usually a training or confidence issue, not a bad agent. Report separately; do not let it inflate escalation integrity.
A16: TRIGGERED = false · HANDLED = false | B16: Any outcome | C16: The ordinary call. No escalation metric applies. | D16: C-0001. | E16: Roughly 88% of calls. Excluded from both numerator and denominator.
A18: TRIGGER LIST
A19: Trigger type | B19: Condition | C19: Detection | D19: Owner it routes to
A20: caller_request | B20: The caller explicitly asks for a supervisor, a manager or someone senior. | C20: Deterministic — verbatim phrase with turn reference. | D20: Operations
A21: compliance_exception | B21: A control exception is detected on the call — no recording disclosure, detail disclosed before verification, a required disclosure omitted. | C21: Deterministic — greeting and verification sequence checks. | D21: Compliance
A22: contested_document | B22: The caller disputes a document or signature on file, such as a broker of record change they did not authorise. | C22: Caller states the dispute; agent confirms a document exists. | D22: Broker Relations, then Compliance
A23: retention_risk | B23: Verbatim exit or market-test language — going out to bid, moving at renewal, cancelling. | C23: Verbatim with turn reference. Inferred intent does not count. | D23: Account Management
A24: clinical_or_safety_risk | B24: The caller describes a health or safety situation requiring urgent care or review. | C24: Model-detected, clinician-reviewed. Score is withheld pending review. | D24: Clinical review
A25: scheduled_care_at_risk | B25: A benefit dispute the agent cannot resolve, where care is already booked within days. | C25: Agent cannot overturn AND a date is stated by the caller. | D25: Operations
A26: authority_limit | B26: A billing correction, reinstatement or retroactive adjustment beyond the agent's authority threshold. | C26: Amount or action type exceeds a configured limit. | D26: Operations / Finance
A27: broker_conduct_adverse | B27: A broker action or omission caused the caller's problem and the caller names the broker aloud. | C27: Named-aloud attribution plus an adverse finding. | D27: Broker Relations

Sheet Call Quality Framework
A1: How a call score is produced
A2: The score is not written by the model. The model reads the transcript and returns quoted evidence; a fixed rubric held in version-controlled configuration does the arithmetic. That separation is the most defensible property of the whole platform: it means the same transcript produces the same score, that changing provider changes cost and latency but never a number, and that every point lost can be traced to a quoted turn. This sheet sets out the mechanism, the verification step that throws evidence away, the two cases where no score is published, and — in the final section — four design decisions that are still open and should be settled before the framework is defended in front of a client.
A4: Stage | B4: How it works | C4: Worked example | D4: Why it is built this way
A5: 1. Evidence extraction | B5: The model reads the transcript and returns markers. Each marker names a dimension, a polarity, a quoted phrase and the turn it came from. The model never returns a number. | C5: On call C0002 the model returned five surviving markers — three positive (empathy, accuracy, proactivity) and two negative (empathy, resolution_ownership). | D5: A model that returns a score cannot be audited, and two providers will disagree. A model that returns quotes can be checked against the transcript mechanically.
A6: 2. Verification | B6: Every marker is checked against the transcript before it can move the score. A marker is refused if the quoted words are not in the cited turn (quote_not_in_turn), the turn does not exist (missing_turn), or the dimension is not in the rubric (unknown_dimension). Refusals are recorded and shown on the call. | C6: A model claimed the agent said 'I can waive that fee for you today' at turn 9, citing a −15 compliance failure. Turn 9 actually reads 'I'll note the dispute and someone will call you back.' Refused, zero points. | D6: This is the step that makes the number auditable. It also turns model hallucination into a measurable property of the model rather than an invisible error in the score.
A7: 3. Arithmetic | B7: Base 100. Negative markers are summed per dimension and capped per dimension per call. Positive markers offset penalties up to a maximum of 15 points and never add above the base. Score = 100 − (capped penalties − offset). | C7: 100 − (18 − 8) = 90. | D7: Caps stop the same criticism phrased five ways from sinking a call. The offset lets genuine good practice soften a poor call without erasing it.
A8: 4. Banding | B8: GOOD at 86 and above, AVERAGE at 60 and above, POOR below 60. | C8: Of 53 calls in the earlier corpus: 18 good, 29 average, 6 poor. | D8: The boundaries are currently empirical rather than outcome-calibrated — see open decision 3 below.
A9: 5. Withholding | B9: Two cases publish no number. Where clinical risk is present, a clinician reviews the call first; the score is visible to the reviewer with the reason attached. Where every marker failed verification, the call is marked Provisional rather than scored. | C9: A call where 0 of 7 markers survived would otherwise come through as a flawless 100. | D9: A call nobody has successfully scored is not a good call. Note the distinction: a call the model read and had no criticism of is a quiet call and stays confirmed — nothing proposed is not the same as nothing surviving.
A10: 6. Versioning | B10: The rubric lives in one configuration file. Weights are data, not code. Every score is stamped with the rubric version that produced it, and old scores keep the version they were judged under. | C10: config/rubric.yaml at v1.0.0. | D10: A tightened rule must be visible in the record, or historical comparison becomes meaningless and a policy change looks like a performance change.
A12: THE SIX DIMENSIONS
A13: Dimension | B13: What it measures | C13: Per + | D13: Per − | E13: Cap − | F13: Worst case from this dimension alone
A14: escalation_appropriateness | B14: Recognising and acting on urgency | C14: 3 | D14: -20 | E14: 40 | F14: 40 points
A15: compliance_disclosure | B15: Required disclosures and conduct | C15: 2 | D15: -15 | E15: 45 | F15: 45 points
A16: accuracy | B16: Factual and procedural accuracy | C16: 2 | D16: -12 | E16: 36 | F16: 36 points
A17: resolution_ownership | B17: Ownership of the member's outcome | C17: 2 | D17: -10 | E17: 30 | F17: 30 points
A18: empathy | B18: Empathy and acknowledgement | C18: 3 | D18: -8 | E18: 24 | F18: 24 points
A19: proactivity | B19: Proactive help beyond the question | C19: 3 | D19: -6 | E19: 18 | F19: 18 points
A21: OPEN DESIGN DECISIONS
A22: # | B22: Issue | C22: Why it matters | D22: Recommendation
A23: 1 | B23: Base 100 cannot distinguish compliant from excellent. | C23: A short, competent, entirely uncriticised call scores 100. An outstanding call scores 95, because positives only offset and never add. The coaching value lives in exactly that gap. | D23: Either drop the base and let good behaviour earn upside, or publish two numbers — a compliance score and a value score — and stop implying one figure covers both.
A24: 2 | B24: The offset is applied to the total, not per dimension. | C24: The deck says positives cannot erase a compliance failure, but the arithmetic does not enforce it. In the worked example, 8 points of empathy praise paid down an 18-point penalty. If one of those penalties had been a disclosure failure, warmth bought off a statutory breach. | D24: Exclude compliance_disclosure and escalation_appropriateness from offset eligibility, and add a hard gate — any compliance negative caps the call at 60 regardless of the arithmetic.
A25: 3 | B25: The 86 boundary is derived circularly. | C25: It sits in the gap between agent averages, so the definition of a good call is set by the cohort currently employed. Hire a stronger team and the threshold moves. | D25: Calibrate against outcomes now that the corpus carries repeat contact, escalation and exit language: find the score that predicts a callback, an escalation or a termination.
A26: 4 | B26: 'Same transcript, same score' is stronger than the design supports. | C26: The arithmetic is provider-independent. The extraction is not — different providers will return different markers from the same call, so the score moves. | D26: Claim that the scoring policy is provider-independent and auditable. Then run the test before a client does: three providers, twenty calls, publish the spread.

Sheet Signal Taxonomy
A1: Signal taxonomy
A2: The allowed values of the signals tag. A signal answers 'what happened on this call'; the Intelligence Register answers 'why should the business care'. Severity drives ranking on the Inferences screen and owner drives routing, so both are mandatory. Signals are counted as distinct types per call, never as occurrences — five instances of one problem is one problem, whereas three different problems on one call is an account coming apart. One new signal is added in v8: process_gap_proposed, which captures an improvement raised inside a call and has a lifecycle rather than dying as a note.
A4: Signal type | B4: Severity | C4: Owner | D4: Definition | E4: Typical trigger
A5: member_communication_gap | B5: MEDIUM | C5: Member Communications | D5: Something the member should have been told at enrollment and was not. | E5: Surprise cost, surprise exclusion, surprise waiting period
A6: process_breakdown | B6: HIGH | C6: Operations | D6: An internal process accepted an input and failed to act on it. | E6: Portal submission not applied, ID never issued, termination still billing
A7: compliance_disclosure_missing | B7: HIGH | C7: Compliance | D7: A required disclosure was not made. | E7: No recording notice; benefit limit not stated where required
A8: verification_failure | B8: CRITICAL | C8: Compliance | D8: Member detail disclosed before identity verification completed. | E8: Agent answers a claim question before confirming the caller
A9: broker_conduct_adverse | B9: HIGH | C9: Broker Relations | D9: A broker action or omission caused the member's problem. | E9: Misstated rule at sale, unsubmitted election, unresponsive for weeks
A10: broker_conduct_positive | B10: LOW | C10: Broker Relations | D10: The broker prepared the client well and shortened the call. | E10: Caller arrives with an accurate written summary and their own dates
A11: escalation_missed | B11: HIGH | C11: Operations | D11: An explicit escalation request went nowhere and no alternative was offered. | E11: Supervisor asked for and refused
A12: retention_risk | B12: CRITICAL | C12: Account Management | D12: Explicit exit or market-test language. | E12: Going out to bid; moving at renewal; cancelling
A13: revenue_opportunity | B13: LOW | C13: Account Management | D13: Interest in a line the group does not hold. | E13: Employer asks what it would take to add vision
A14: knowledge_error | B14: MEDIUM | C14: Knowledge Management | D14: An agent stated a published rule incorrectly. | E14: Waiting period type confused; out-of-state availability misstated
A15: network_adequacy | B15: MEDIUM | C15: Product / Network | D15: A covered benefit is unusable where the member lives or works. | E15: Out-of-state employee with no chiro provider
... A17: process_gap_proposed | B17: MEDIUM | C17: Process Owner (by touchpoint) | D17: An improvement to a document, system or process proposed or clearly implied inside the call, by the agent or the caller. Carries a lifecycle: unvalidated, validated, actioned or rejected. | E17: 'The letter should say which waiting period and when it ends'; 'nobody told me that at enrolment'

Sheet Touchpoints
A1: Member and employer touchpoints
A2: Where a failure originated, as distinct from where it surfaced. A member who does not understand a waiting period surfaced the problem on a call, but the failure happened at the enrolment meeting, in the enrolment material, or in a denial letter that said 'ineligible' and stopped. Tagging the touchpoint is what turns a pile of individual calls into a ranked list of documents and moments to fix, and it is the dimension that makes knowledge failures and process gaps actionable by someone who does not run the call centre. This is the sheet a change and knowledge management function would work from.
A4: Touchpoint | B4: Owner | C4: Who controls the content | D4: Typical failures that originate here | E4: Rules most often misstated here
A5: enrolment_meeting | B5: Broker Relations | C5: The broker, not Choice | D5: Product rules misstated at the point of sale; participation minimums misdescribed; waiting periods denied | E5: P-21, P-23, P-25, P-28, C-12
A6: enrolment_material | B6: Marketing / Product | C6: Choice | D6: Distinction between the employer waiting period and carrier waiting periods never drawn; takeover credit not explained | E6: P-14, P-29, C-12
A7: enrolment_form | B7: Operations | C7: Choice | D7: Waiver section not completed; life enrolment missed for a dental-waiving employee | E7: P-22, P-30, P-31
A8: welcome_pack | B8: Member Communications | C8: Choice | D8: Member never learns which carrier they are on, or that a DHMO requires an assigned dentist | E8: C-01, C-02, P-10
A9: id_card_mailer | B9: Operations | C9: Choice and the carriers | D9: Cards routed to the employer and never distributed; mid-year line additions missing the production run | E9: P-31
A10: denial_letter_eob | B10: Carrier | C10: The carrier | D10: Reason given as 'ineligible' with no waiting period named and no eligibility date; cost share not explained | E10: C-12, C-16, C-08
A11: invoice_statement | B11: Operations / Finance | C11: Choice | D11: Leavers still billed; change codes unexplained; admin fee stepping between bands unannounced | E11: A-09, A-27, A-45, P-33
A12: employer_portal | B12: Digital | C12: Choice | D12: Submission accepted with no confirmation that it was applied; undiagnostic upload errors | E12: A-02, A-07, A-10
A13: renewal_pack | B13: Account Management | C13: Choice | D13: Participation position not flagged before the anniversary; network gaps for out-of-state staff not surfaced before a line is bought | E13: P-18, P-36, C-28
A14: broker_material | B14: Broker Relations | C14: The broker | D14: Plan comparison presented as fact; takeover credit assumed | E14: P-28, P-29, C-19
A15: agent_conversation | B15: Operations | C15: Choice | D15: The rule stated incorrectly on the call itself | E15: Any
A16: cobra_notice | B16: Compliance | C16: Choice for Cal-COBRA, the employer for federal | D16: Notice sent to a stale address; employer assuming Choice sent a federal notice it did not send | E16: A-34, A-38, A-39, A-42

Sheet Metrics
A1: Metrics — 12 published, 2 base measures
A2: Consolidated from an earlier list of twenty-four. The reduction came from separating what the pipeline tags from what the platform calculates: most of the original twenty-four were the same calculation pointed at a different tag. Complaint rate by employer and by broker are one metric with a dimension; first-contact resolution and resolution rate by category are one metric with a filter; escalation rate and refusal rate are inverses of each other. Every metric here is one of four calculation patterns, so the development team builds four functions and dimensions them rather than twenty-four reports. The Build note column carries the failure mode for each — read those before implementing.
A4: # | B4: Metric | C4: Pattern | D4: Plain-English meaning | E4: Numerator | F4: Denominator | G4: Dimensions | H4: Window | I4: Min n | J4: Replaces | K4: Build note / risk
A5: 1 | B5: Contact rate | C5: Normalised rate | D5: How often a given population picks up the phone, per 1,000 people covered, per year. | E5: Calls matching the dimension filter × (52 ÷ weeks) | F5: Lives enrolled in that population ÷ 1,000 | G5: Product line · employer · industry · region | H5: 12wk | I5: 30 | J5: Contact rate by product line; industry rate | K5: Population must be the calls' own population. Dividing sample calls by book-wide enrollment is the classic denominator error.
A6: 2 | B6: Complaint rate | C6: Normalised rate | D6: How much dissatisfaction a group or a broker generates relative to their size — so dysfunction outranks size. | E6: Calls with complaint.present and the given attributed_to | F6: Employer: lives ÷ 100. Broker: groups in book | G6: Employer · broker · attribution target | H6: 12wk | I6: 10 calls | J6: Complaint rate — employer; complaint rate — broker | K6: Always show the raw count beside the rate. Broker rate uses book size from reference data, never from call counts.
A7: 3 | B7: First-contact resolution | C7: Share | D7: Share of calls that actually ended the problem — no one called back about it. | E7: RESOLVED with no related contact from the same caller ≤14 days | F7: All calls with a resolution outcome | G7: Category · agent · product line · queue | H7: 4wk | I7: 30 | J7: FCR; resolution rate by category | K7: PARTIALLY_RESOLVED and ESCALATED sit in the denominator, not the numerator. One denominator across the whole platform.
A8: 4 | B8: Failure-driven repeat rate | C8: Share | D8: When we fail to fix it, how often does the person come back — and what does that cost us. | E8: UNRESOLVED calls followed by a contact from the same caller ≤14 days | F8: All UNRESOLVED calls in window | G8: Category · employer · product line · agent | H8: 12wk | I8: 30 | J8: Repeat contact rate; failure-driven repeat; cost of first-contact failure | K8: Exclude the last 14 days of the window — those calls have no exposure period. The cost view is Σ AHT of the repeats, same metric.
A9: 5 | B9: Self-inflicted demand | C9: Share | D9: How much of our call volume we caused ourselves rather than the member needing something new. | E9: Failure-driven repeats + calls chasing an already-submitted action + calls caused by a logged process defect | F9: All calls in window | G9: Category · employer · defect type | H9: 12wk | I9: 60 | J9: Self-inflicted demand | K9: Publish the three components separately so a reader can dispute one without discarding the total.
A10: 6 | B10: Escalation integrity | C10: Share | D10: When a call genuinely needed a supervisor, did it get one. | E10: Calls with escalation.handled = true | F10: Calls with escalation.triggered = true | G10: Agent · trigger type · queue | H10: 12wk | I10: 30 triggers | J10: Escalation rate; escalation refusal rate | K10: Refusal rate is the inverse view of the same metric. Against all calls 0% reads as good news; against warranted calls it reads as a control failure.
A11: 7 | B11: Control exception rate | C11: Share | D11: How often we broke our own compliance rules on a call. | E11: Calls with ≥1 control_exception, by type | F11: All calls requiring that control | G11: Exception type · agent · queue | H11: 4wk | I11: 30 | J11: Disclosure omission rate; verification failure rate | K11: Deterministic — no model judgement. Owner is Compliance, not the call centre. Report by exception type, not as one blended number.
A12: 8 | B12: Knowledge failure rate | C12: Share | D12: How often we told someone something that was factually wrong, and which rule we got wrong. | E12: Calls with knowledge_failure.present | F12: All calls in window | G12: Rule ID · product line · agent | H12: 4wk | I12: 30 | J12: Knowledge failure rate | K12: Must roll up by rule ID. The output is a list of knowledge base articles to rewrite, ranked by call count.
A13: 9 | B13: Cost to serve | C13: Time aggregate | D13: How many minutes of our people a covered life consumes in a year — against a flat per-group fee. | E13: Σ aht_seconds × (52 ÷ weeks) ÷ 60 | F13: Lives enrolled in that population | G13: Product line · employer · industry | H13: 12wk | I13: 30 | J13: Cost to serve | K13: The margin metric. Admin fee is flat per group regardless of service consumed, so this is margin variance made visible.
A14: 10 | B14: Account risk flag | C14: Composite flag | D14: Which employers are showing warning signs across more than one dimension at once. | E14: Employers meeting ≥2 of: complaint rate up month-on-month · a failure-driven repeat · market_test intent · a CHOICE-attributed UNRESOLVED inside the renewal window | F14: Employers with ≥3 calls in window | G14: Employer · renewal month · broker | H14: 12wk | I14: 10 calls per employer | J14: Signal density; account at risk; revenue at risk | K14: NOT a churn prediction and must never be labelled one — no termination outcomes exist in this dataset to validate against. Revenue at risk is a display of this metric: Σ premium of flagged employers. Signal density is its input.
A15: 11 | B15: Commercial intent capture | C15: Share | D15: How often someone told us they want to buy more, or want to leave — and whether anyone acted. | E15: Calls with intent expansion / market_test / cancellation | F15: All calls in window | G15: Intent type · employer · broker · routed yes/no | H15: 12wk | I15: 10 | J15: Expansion intent; market-test language | K15: Verbatim with turn reference. The routed flag is the finding: in the current service model, none of it reaches sales.
A16: 12 | B16: Agent quality score | C16: Composite flag | D16: How well one agent handled one call, with the evidence that produced the number. | E16: 100 − capped penalties + offset (max 15) | F16: n/a — per call | G16: Agent · category · product line · tenet | H16: per call | I16: n/a | J16: Agent quality score; % calls clean (tenet) | K16: Tenet clean % is a view over the same markers: calls with zero negative markers in a tenet ÷ all calls. Binary and unweighted — state the applicable-calls caveat on the tile.
A17: B1 | B17: Call volume | C17: Base measure | D17: How many calls, cut any way. | E17: Count of calls | F17: n/a | G17: any | H17: any | I17: — | J17: — | K17: The denominator for most shares above.
A18: B2 | B18: AHT | C18: Base measure | D18: Average talk time per call. | E18: Σ aht_seconds | F18: Call count | G18: any | H18: 4wk | I18: 30 | J18: AHT | K18: Never publish as a target. In this dataset the best agents run longest and the worst run shortest, so an AHT target ranks the poor tier first.
A20: Dropped | B20: Repeat contact rate for any reason — removed, because it can rise when service improves and is therefore not a quality signal; retained only as context inside metric 4. Signal density and revenue at risk — folded into metric 10 as an input and a display. Resolution rate by category — a dimension of metric 3, not a metric.

Sheet Intelligence Register
A1: Intelligence register
A2: This replaces the Claims Register, and the change is more than a rename. A claim is a finding; intelligence is a finding an executive can act on. Each entry therefore runs through three layers — the signal that fired, what the pattern means to the business, and the decision it supports — and is filed under one of seven lenses rather than sitting in a flat list. Seven is deliberate: the same discipline that reduced twenty-four metrics to twelve applies here, and a taxonomy with twenty categories is a taxonomy nobody navigates. The Sufficiency column is the honest part — it says whether 360 calls can actually support the statement, and where it cannot, the entry is reframed to a wider window rather than published with a small denominator.
A4: # | B4: Lens | C4: Business question it answers | D4: What the platform says | E4: Evidence behind it | F4: Population | G4: Who acts | H4: Action implied | I4: Sufficiency at 360 | J4: Drill path
A5: 1 | B5: CUSTOMER | C5: Which customers need attention, and how soon? | D5: Three employers are behind a fifth of all complaints about us, and two of them renew in January. | E5: Complaints per 100 enrolled, cross-referenced with renewal month from reference data | F5: ~18 calls each | G5: Account Management | H5: Three named calls to make this month, before the renewal packs go out | I5: Sufficient. Also run the shared-broker check automatically — if two of the three use the same broker it is one problem, not three | J5: Lens → employer → calls → quoted turn
A6: 2 | B6: CUSTOMER | C6: Which accounts are deteriorating across more than one dimension at once? | D6: Twelve to sixteen employers meet two or more risk conditions. Five renew inside 90 days. | E6: Composite of complaint-rate movement, failure-driven repeats, exit language and unresolved calls in the renewal window | F6: 12–16 employers | G6: Account Management | H6: A watchlist with dates, reviewed weekly | I6: Sufficient to name a list. Explicitly not a churn prediction — there is no termination history here to validate against | J6: Lens → watchlist → account → signals → calls
A7: 3 | B7: CUSTOMER | C7: What are these accounts worth if we lose them? | D7: Flagged accounts represent N groups, M employees and roughly $X of annual premium. | E7: Annual premium from reference data, summed over flagged employers | F7: 12–16 employers | G7: Adam / Account Management | H7: Prioritise retention effort by exposure, not by noise | I7: Sufficient. Present as exposure, never as expected loss — we have no probability to apply to it | J7: Lens → total → account list → account
A8: 4 | B8: OPERATIONS | C8: How much of our call volume did we create ourselves? | D8: Roughly one call in five exists because we failed somewhere upstream. | E8: Failure-driven repeats, plus calls chasing an already-submitted action, plus calls caused by a logged process defect | F8: ~70 calls | G8: Adam / Operations | H8: Investigate the top three causes; each has a named remediation | I8: Sufficient. Publish the three components separately so a reader can dispute one without binning the total | J8: Lens → component → cause → calls
A9: 5 | B9: OPERATIONS | C9: Where does the process break, and what does it cost? | D9: Three systemic process failures drive recurring demand: portal submissions that are accepted and not applied, terminations that keep billing, and cards that are never issued on mid-year line additions. | E9: process_breakdown and billing_defect signals, aggregated by touchpoint | F9: Varies by defect | G9: Operations / Digital | H9: A ranked backlog with call counts and minutes attached | I9: Sufficient for the top three by volume | J9: Lens → touchpoint → defect → calls
A10: 6 | B10: OPERATIONS | C10: When people asked for help beyond the agent, did they get it? | D10: People asked to speak to someone senior 43 times. In 25 of those nothing happened and no alternative was offered. | E10: escalation.requested_by_caller against escalation.handled | F10: 43 requests | G10: Operations | H10: A routing path that exists, and agent authority to use it | I10: Sufficient. Almost no interpretation involved, which makes it a good first proof of the evidence model | J10: Lens → refused calls → quoted turn
A11: 7 | B11: FINANCIAL | C11: Where is operational capacity actually going? | D11: A life member consumes roughly four times the service minutes of a dental member, and a chiropractic member about two and a half times. | E11: Talk time per enrolled life per year, by product line | F11: 32 calls on the thinnest line | G11: Adam | H11: Review whether administration economics match service consumption | I11: Sufficient. Chiro is the binding cell at 32 calls | J11: Lens → line → employers → calls
A12: 8 | B12: FINANCIAL | C12: Is what we charge aligned with what we spend? | D12: The administration fee steps by headcount — $25, $30, $35, $50 — and never by service consumed. A 21-life group and a 199-life group both pay $35. | E12: Fee bands from rule P-33 against cost-to-serve by employer | F12: All 70 employers | G12: Adam | H12: A pricing and product design question, not a call centre one | I12: Sufficient. The fee bands are published fact; the service variance is measured | J12: Lens → band → employer → cost to serve
A13: 9 | B13: FINANCIAL | C13: What is first-contact failure costing us? | D13: When we do not fix it first time, 38% of people call back within two weeks. That is N hours a month spent on things we already discussed. | E13: Unresolved calls followed by a contact from the same caller within 14 days, and the minutes those took | F13: 76 unresolved | G13: Adam / Operations | H13: Fund the fix for the top cause | I13: Sufficient. Exclude the last 14 days of the window — those calls have not had time to come back | J13: Lens → cause → repeat pairs → calls
A14: 10 | B14: COMMERCIAL | C14: What are customers trying to buy that we are not selling them? | D14: Fourteen employers asked about products they do not hold, covering N employees. None of it reached anyone in sales. | E14: intent = expansion, verbatim, with the routed flag | F14: 18 calls | G14: Adam / Sales | H14: A routing rule that sends expansion intent to account management the same day | I14: Sufficient. The routed flag is the finding — in the current service model it is never routed | J14: Lens → intent → employer → quoted turn
A15: 11 | B15: COMMERCIAL | C15: Who is telling us they are leaving, and are we hearing it? | D15: Fourteen employers used explicit exit or market-test language. In most cases the call ended with a note on the account. | E15: intent = market_test or cancellation, verbatim, against escalation.handled | F15: 14 calls | G15: Account Management | H15: Treat exit language as an escalation trigger, not a sentiment tag | I15: Sufficient to name a list, not to quote a rate | J15: Lens → intent → account → calls
A16: 12 | B16: PRODUCT | C16: Which benefits exist on paper but cannot be used in practice? | D16: Chiropractic is unusable for employees outside California, because Landmark's insured plans are California-only and there is no out-of-network payment at all. | E16: network_adequacy signals joined to employer region and workforce distribution | F16: Employers with out-of-state staff | G16: Product / Network Management | H16: A census-versus-network check at quotation, and plain-language geographic limits in the employer confirmation | I16: Sufficient to name the pattern. Rule C-28 and C-29 make it factual rather than anecdotal | J16: Lens → line → employer → calls
... A22: 18 | B22: ORGANIZATION | C22: Which brokers are underserving their clients, including the ones we cannot see today? | D22: Three brokers sit far above the channel median on complaints per client. All three have fewer than six clients — which is precisely why nobody has noticed them. | E22: Named-aloud broker attribution divided by groups in book, against the channel median | F22: 4–6 calls per broker | G22: Rebekah / Broker Relations | H22: A conversation with three agencies, and a rate-based watchlist rather than a volume one | I22: Enough to name three. Not enough for a precise rate — say 'well above average', not '8.5 times' | J22: Lens → broker → groups → calls
A24: Dropped | B24: '25% of calls last week were repeats' — at 30 calls a week that is about seven calls and says nothing; entry 9 replaces it. 'Half of last week's unresolved calls were billing' — that is two calls; the resolution-rate-by-category view replaces it. Both were right in shape and wrong in window. The fix is the timeframe, not the sample.

Sheet Questions Worth Asking
A1: Questions worth asking — trigger rules
A2: The platform should not only answer questions that were asked; it should notice when the evidence has become unusual and propose the question worth asking next. This sheet is that capability, written honestly as a rules engine with explicit thresholds rather than presented as emergent insight. Every trigger is a stated condition with a stated number, and the reason for each threshold is recorded so it can be argued with and tuned. That transparency is the point: a rules file someone can read and change is defensible, whereas a dashboard that implies intuition it does not have will not survive the first person who asks how it works.
A4: # | B4: Trigger rule (explicit) | C4: Question surfaced | D4: Lens | E4: What answering it requires | F4: Why the threshold sits here
A5: 1 | B5: ≥4 employers raise the same signal type at the same touchpoint within a rolling 4 weeks | C5: Is this a common process defect rather than four unrelated incidents? | D5: OPERATIONS | E5: Group the calls by touchpoint and defect, and check whether they share a carrier, a region or a broker | F5: Four is the point at which coincidence becomes unlikely at this volume, and it is the smallest number that can be broken down one level further and still show a pattern
A6: 2 | B6: ≥3 calls name the same broker adversely within a rolling 12 weeks, from ≥2 different employers | C6: Is this isolated to one unhappy client or systemic across this broker's book? | D6: CUSTOMER | E6: Pull the broker's groups from the Broker Master and check how many of their book appear at all | F6: Two employers rules out a single disgruntled client. Three calls is the minimum that can distinguish a pattern from a bad week
A7: 3 | B7: A product line's contact rate per 1,000 enrolled exceeds 2× the corpus median | C7: Is the service burden concentrated in a particular employer type or plan configuration? | D7: FINANCIAL | E7: Break the line's calls down by employer size, industry and plan design | F7: 2× is where the difference stops being explainable by enrolment mix alone
A8: 4 | B8: An employer's complaint rate rises for 2 consecutive 4-week windows AND their renewal falls within 90 days | C8: Should this account be moved to active retention before the renewal pack goes out? | D8: CUSTOMER | E8: Open the account's calls in date order and read what changed between the two windows | F8: Two consecutive windows filters noise. 90 days is the point at which intervention is still possible
A9: 5 | B9: ≥5 calls in a rolling 4 weeks cite the same rule_id in a knowledge_failure | C9: Is this a training problem, a process problem, or an information-design problem? | D9: ORGANIZATION | E9: Check whether the failures cluster on one agent (training), one touchpoint (information design) or across both (process) | F9: Five separates a rule people get wrong from a person who got it wrong
A10: 6 | B10: ≥3 calls propose the same process_gap at the same touchpoint | C10: Should this document or screen be rewritten, and what would it save? | D10: ORGANIZATION | E10: Aggregate the proposals, attach the call minutes consumed, and route to the touchpoint owner | F10: Three independent people proposing the same change is stronger evidence than any single articulate one
A11: 7 | B11: Escalation refusal rate exceeds 40% in a rolling 12 weeks | C11: Do our agents have a route to escalate, or have we asked them to hold a line they cannot hold? | D11: OPERATIONS | E11: Check refusals by trigger type — a refusal on retention risk means something different from one on a billing limit | F11: 40% is the point at which the cause is more likely structural than individual
A12: 8 | B12: An employer generates ≥2 calls with unrouted expansion intent in a rolling 12 weeks | C12: Why has an account asking to buy more not reached anyone who can sell to them? | D12: COMMERCIAL | E12: Open both calls and check whether the same line was asked about twice | F12: Twice is intent. Once is a question
A13: 9 | B13: A control exception type occurs on ≥3 calls handled by the same agent in a rolling 4 weeks | C13: Is this an individual habit or a gap in what we told everybody? | D13: RISK | E13: Compare that agent's rate to the cohort rate for the same exception type | F13: Three from one agent in four weeks is a habit; below that it is chance
A14: 10 | B14: A group's payment or participation position changes AND a complaint is logged within the same 4 weeks | C14: Are the conversation and the account record telling the same story? | D14: CUSTOMER | E14: This requires the transactional join that is currently out of scope — the rule is defined and dormant | F14: Recorded here deliberately so the capability is designed for, even though the data is parked
A16: Discipline | B16: A surfaced question must be answerable by the platform within two clicks, or it should not be surfaced. Thresholds are configuration, not code, and every threshold change is versioned like a rubric change. Trigger 10 is included while dormant so that the model does not have to be redesigned when the transactional data arrives.

Sheet Rules — Program
A1: Program layer — what a group may buy
A2: Set by ChoiceBuilder and sourced from the Program Guidelines, the Underwriting Guidelines and the Employer Application. These rules decide what an employer is permitted to buy, who is eligible for it, what they must contribute and what participation they must maintain, and they govern most employer conversations at sale and at renewal. Every row carries its source document and a confidence value. Nothing marked UNVERIFIED — shaded amber — may be used to assert that an agent gave wrong information or that a member was misinformed; it may only be used to shape a question. Tagging a knowledge failure against a rule that turns out not to exist is worse than not tagging it at all.
A4: Rule ID | B4: Area | C4: Rule | D4: Commonly confused with | E4: Source | F4: Confidence
A5: P-01 | B5: Group eligibility | C5: Group size 2–500 eligible employees. | D5: ChoiceBuilder being small-group only. | E5: Program Guidelines | F5: VERIFIED
A6: P-02 | B6: Group eligibility | C6: The group's home office must be domiciled in California. The address cannot be a PO Box. | D6: Employees needing to be in California. | E6: Program Guidelines; Underwriting Guidelines | F6: VERIFIED
A7: P-03 | B7: Group eligibility | C7: Valid federal tax ID (not an SSN), matching the group applying, and a company business checking account. | D7: Sole proprietors being ineligible. | E7: Program Guidelines; Underwriting Guidelines | F7: VERIFIED
A8: P-04 | B8: Group eligibility | C8: PEO sub-groups are eligible. A company leasing out workers may enrol only its core staff — leased-out workers are not eligible through the leasing company, which must itself have a California office. | D8: All workers on a leasing company's books being eligible. | E8: Program Guidelines; Underwriting Guidelines | F8: VERIFIED
A9: P-05 | B9: Group eligibility | C9: Owners and partners are eligible to enrol as employees. | D9: Owners being excluded as non-employees. | E9: Underwriting Guidelines | F9: VERIFIED
A10: P-06 | B10: Employee eligibility | C10: Four conditions must all be met and kept: meet the employer's waiting period; be actively working the hours the employer requires; be a permanent employee not eligible for union-offered coverage; and be paid salary or hourly, not 1099 or commission. | D10: Any worker on the payroll qualifying. | E10: Employer Admin Guide, Coverage Eligibility Requirements | F10: VERIFIED
A11: P-07 | B11: Employee eligibility | C11: The employee must live or work in the plan's service area. | D11: Nationwide availability. | E11: Underwriting Guidelines | F11: VERIFIED
A12: P-08 | B12: Employee eligibility | C12: Minimum working hours for eligibility is a group election — 20+ or 30+ hours per week in California — and can only be changed at renewal. | D12: A fixed 30-hour or 40-hour rule. | E12: Employer Admin Guide, Change in Group Policy | F12: VERIFIED
A13: P-09 | B13: Plan selection | C13: Dental is mandatory. An employer must offer dental to enrol with ChoiceBuilder, and must offer one PPO carrier alongside the DeltaCare USA DHMO. Only ONE PPO carrier may be chosen. | D13: Vision-only or chiro-only groups, which do not exist. | E13: Underwriting Guidelines; Program Guidelines | F13: VERIFIED
A14: P-10 | B14: Plan selection | C14: One vision carrier and one life carrier per group. All family members must select the same carrier and the same benefit design. | D14: Employee-level or family-member-level carrier choice. | E14: Program Guidelines; Employer Admin Guide FAQs | F14: VERIFIED
A15: P-11 | B15: Effective dates | C15: First of the month only. Employers may apply up to 60 days in advance; the rate in force at the effective date applies. The group may not change its effective date after approval. | D15: The quoted rate being locked at application. | E15: Program Guidelines; Underwriting Guidelines | F15: VERIFIED
... A41: P-37 | B41: Contracts | C41: Contracts (Group Service Agreement and/or Master Policy) are held by the ChoiceBuilder Welfare Benefit Insurance Master Trust and are downloadable by the group from the Forms tab after login. | D41: The employer holding the policy directly. | E41: Employer Admin Guide, Welcome | F41: VERIFIED

Sheet Rules — Administration
A1: Administration layer — what happens after the sale
A2: Sourced almost entirely from the ChoiceBuilder Employer Administrative Guide, which we found late and which turned out to be the most complete single document in the set. These rules govern enrolment, mid-year changes, terminations, dependent eligibility, billing, grace periods, COBRA and Cal-COBRA, and the renewal timeline — in other words, most of what an employer actually calls about. What makes this layer valuable for the platform is that nearly every rule carries a date or a deadline, so an agent is either right or wrong against a published document rather than against an opinion. That makes it the best available material for a knowledge failure metric.
A4: Rule ID | B4: Area | C4: Rule | D4: Commonly confused with | E4: Call scenarios it generates | F4: Source | G4: Confidence
A5: A-01 | B5: New hires | C5: New employees and dependents are eligible the first day of the month following completion of the group's waiting period. | D5: The waiting period end date itself being the effective date. | E5: New hire given the wrong start date; employee hired on the 2nd waiting almost two months. | F5: Employer Admin Guide | G5: VERIFIED
A6: A-02 | B6: New hires | C6: The Enrollment Form must reach ChoiceBuilder no more than 60 days before, and no more than 30 days after, the employee's effective date. | D6: An open-ended submission window. | E6: Form submitted on day 45 and rejected. | F6: Employer Admin Guide | G6: VERIFIED
A7: A-03 | B7: Military leave | C7: An employee previously covered before military service may re-enrol without completing the waiting period. The form must arrive within 60 days of return to work with a written request to waive the waiting period. | D7: The waiting period restarting. | E7: Returning reservist told to wait 90 days. | F7: Employer Admin Guide | G7: VERIFIED
A8: A-04 | B8: Rehires | C8: A rehire may skip the waiting period if they previously completed it, were previously enrolled, are rehired within six months of losing ChoiceBuilder coverage, and re-enrol in the SAME benefits. Effective first of the month following rehire. | D8: Any rehire skipping the wait. | E8: Seasonal worker rehired at seven months and made to wait. | F8: Employer Admin Guide | G8: VERIFIED
A9: A-05 | B9: Voluntary termination | C9: An employee withdrawing coverage takes effect the last day of the month FOLLOWING receipt. It is NOT processed retroactively, and the employee cannot re-enrol until renewal. | D9: Immediate or backdated cancellation. | E9: Employee wanting a refund for a month already billed. | F9: Employer Admin Guide | G9: VERIFIED
A10: A-06 | B10: Involuntary termination | C10: Coverage is cancelled at the end of the month following the last day employed, eligible, or date of death. Where a termination or loss of hours falls on the last day of a month, coverage ends that same day. | D10: Coverage ending on the termination date. | E10: Leaver surprised they still had cover; employer billed an extra month they expected not to be. | F10: Employer Admin Guide | G10: VERIFIED
A11: A-07 | B11: Terminations | C11: Notification must not be sent before the last day of employment — requests made earlier cannot be processed. The form must be signed by an authorised group contact on file. | D11: Filing a termination in advance. | E11: Employer filing early in good faith and the termination silently failing. | F11: Employer Admin Guide | G11: VERIFIED
A12: A-08 | B12: Terminations | C12: Cal-COBRA requires the employer to notify ChoiceBuilder of ALL employee terminations within 30 days of the last day employed. | D12: A courtesy timescale. | E12: Late notification creating a Cal-COBRA exposure. | F12: Employer Admin Guide | G12: VERIFIED
A13: A-09 | B13: Billing adjustments | C13: Employers must not self-adjust the statement. Payment must be made in full as billed. ChoiceBuilder credits the premium on the statement FOLLOWING the processing of the termination. | D13: A corrected invoice arriving immediately. | E13: High-churn group paying for leavers and chasing credits — the single most common billing complaint. | F13: Employer Admin Guide | G13: VERIFIED
A14: A-10 | B14: Billing verification | C14: The employer is told to check the invoice immediately after a termination request and to call if the employee and premium still appear. | D14: The system confirming silently. | E14: The employer who did not check and is six cycles out. | F14: Employer Admin Guide | G14: VERIFIED
A15: A-11 | B15: Late enrolment | C15: Permitted for loss of other coverage beyond the employee's control, exhaustion or dramatic reduction of employer contributions toward other coverage, or a change in family status. The group's waiting period must already be satisfied. Effective first of the month following receipt of all forms and documentation. | D15: Open enrolment being the only route. | E15: Employee who waived, then lost a spouse's coverage. | F15: Employer Admin Guide | G15: VERIFIED
... A50: A-46 | B50: Full-roster billing | C50: Monthly full-roster reconciliation as an alternative to transactional submission. | D50: — | E50: Two transcripts offer this as a remedy. | F50: No published citation found. The Admin Guide describes only per-employee forms — this may not exist. | G50: UNVERIFIED

Sheet Rules — Carrier
A1: Carrier layer — what a member actually receives
A2: Set by the carriers rather than by ChoiceBuilder, and sourced from evidence-of-coverage documents, plan summaries and carrier member material. Waiting periods, annual maximums, frequency limits, network rules, referral requirements and conversion rights all live here, and so does most member confusion. Earlier versions of this workbook had almost none of this layer, which is precisely why member call reasons read thin and generic. One caution on numbers: a rule marked VERIFIED is verified as a rule of that carrier's plan family, but the specific figures — copays, allowances, maximums, visit limits — vary by the design a group selected and live on that group's own benefit summary. A transcript must never quote a figure as fact unless it comes from that group's design.
A4: Rule ID | B4: Carrier / line | C4: Rule | D4: Commonly confused with | E4: Source | F4: Confidence
A5: C-01 | B5: DeltaCare USA — DHMO | C5: Benefits are payable only through the assigned contract dentist. Out-of-network is not covered except emergencies. | D5: A PPO, where any dentist can be used at a lower level. | E5: DeltaCare USA EOC | F5: VERIFIED
A6: C-02 | B6: DeltaCare USA — DHMO | C6: Specialist care requires a referral from the assigned general dentist AND preauthorization by Delta Dental. | D6: Self-referral to an in-network specialist. | E6: DeltaCare USA EOC | F6: VERIFIED
A7: C-03 | B7: DeltaCare USA — DHMO | C7: Dependent children may see a pediatric dentist through age 13 without a referral. | D7: The adult referral rule applying to children. | E7: Delta Dental member site | F7: VERIFIED
A8: C-04 | B8: DeltaCare USA — DHMO | C8: Out-of-area emergency care is covered subject to the plan limit; out-of-area generally means 35+ miles from the assigned dentist. | D8: Routine care while travelling. | E8: DeltaCare USA EOC | F8: VERIFIED
A9: C-05 | B9: DeltaCare USA — DHMO | C9: Where no DeltaCare specialist is within the lesser of 35 miles or one hour's commute, the member is authorized to use a PPO, Premier or non-network specialist. | D9: Out-of-network never being available. | E9: Delta Dental plan comparison | F9: VERIFIED
A10: C-06 | B10: DeltaCare USA — DHMO | C10: Each family member MAY choose a different Primary Care Dentist, and may change it by contacting Delta Dental — some restrictions apply. | D10: All family members sharing one dentist. | E10: Employer Admin Guide FAQs | F10: VERIFIED
A11: C-07 | B11: DeltaCare USA — DHMO | C11: Members should not receive bills for care provided or approved by their dental office; if they do, Delta Dental customer service handles it. | D11: The member owing the balance. | E11: Employer Admin Guide FAQs | F11: VERIFIED
A12: C-08 | B12: DeltaCare USA — DHMO | C12: No annual deductible; fixed copayments per procedure. Coordination of benefits does not apply. | D12: Coinsurance; dual coverage reducing cost. | E12: DeltaCare USA EOC; Delta plan comparison | F12: VERIFIED
A13: C-09 | B13: DeltaCare USA — DHMO | C13: California only; the member must live in a served zip code service area. | D13: National availability. | E13: Delta Dental plan pages | F13: VERIFIED
A14: C-10 | B14: DeltaCare USA — DHMO | C14: Frequency limits apply — e.g. bitewing x-rays limited to one series of four films per six months. | D14: Unlimited preventive care. | E14: DeltaCare USA EOC | F14: VERIFIED
A15: C-11 | B15: DeltaCare USA — DHMO | C15: If the assigned dentist's contract ends, work already started is completed, and continuity of care may be available on specific request. | D15: Care ending immediately. | E15: DeltaCare USA EOC | F15: VERIFIED
... A43: C-39 | B43: Anthem / Delta PPO / EyeMed | C43: Full plan design — waiting periods, maximums, frequencies, allowances — for these specific ChoiceBuilder designs. | D43: Ameritas or MetLife terms, which differ. | E43: Benefit Summary CB.5234 exists and is public; the per-design detail has not yet been extracted in full. | F43: UNVERIFIED

Sheet Corrections & Sources
A1: Corrections, open items and source documents
A2: The record of what earlier versions got wrong, what remains unanswered, and where every verified rule comes from. This sheet exists because the rules were originally built from a single member-facing FAQ page and labelled a source of truth, which produced eight factual errors, three of them serious enough to invalidate sample transcripts. It is kept visible rather than quietly fixed so that anyone relying on a rule can see how the rule set has moved, and so the same mistake is harder to repeat.
A4: # | B4: What we said | C4: What the documents say | D4: Source | E4: Impact | F4: Severity
A5: 1 | B5: Voluntary lines carry a 25% minimum participation requirement. | C5: No percentage minimum exists on voluntary lines. Voluntary vision and voluntary chiropractic have NO minimum at all. Voluntary dental works on headcount: Anthem 5 eligible / 2 enrolled; all other dental 10 eligible / 5 enrolled (2–9 groups: MetLife 2 / 2). The 70% requirement belongs to EMPLOYER-SPONSORED dental and vision. | D5: Program Guidelines, Steps 1–3 | E5: v7 transcript C-0010 collapses entirely. v6 call #26R same error. Rule R-17. | F5: CRITICAL
A6: 2 | B6: Members elect life cover and hit an individual guaranteed issue threshold. | C6: Life is employer-sponsored only, 100% participation, 100% employer-paid. There is no employee election. Guaranteed issue exists but at group level — a statement of health is required for all eligible employees only where the EMPLOYER requests an amount above guaranteed issue. | D6: Program Guidelines Step 4; Employer Admin Guide, Change in Group Policy | E6: v7 transcript C-0008 describes something that cannot happen. Rule R-14. | F6: CRITICAL
A7: 3 | B7: Landmark out-of-network chiropractic is reimbursed at a lower rate. | C7: Landmark does not pay for out-of-network services at all; the member bears the full cost. Insured plans exist in California only. | D7: Landmark member notice; Landmark Healthplan | E7: v7 transcript C-0002 offers a remedy that does not exist. v6 call #70R same. Rule R-13. | F7: CRITICAL
A8: 4 | B8: Ortho carries a waiting period, stated as a universal rule. | C8: Ortho AVAILABILITY is gated by carrier and group size before any waiting period. Takeover credit is available at initial enrolment only, and the 12-month wait is waived on proof of 12 consecutive months of prior coverage, with no partial credit. MetLife ortho takeover credit is automatic for groups with prior coverage. An ortho bill from the 12 months before the effective date, showing ortho coverage, is required. | D8: Program Guidelines; Underwriting Guidelines; Employer Application CB0210A | E8: Rule R-03. Any ortho scenario under 10 lives needs checking against carrier. | F8: HIGH
A9: 5 | B9: The administration fee is flat per group. | C9: Banded by headcount — $25 (2–8), $30 (9–20), $35 (21–199), $50 (200+) — and recalculated monthly on the number of employees enrolled in any coverage at the time of invoicing, so it can change month to month. | D9: Program Guidelines; Employer Admin Guide, Billing | E9: Metrics sheet metric 9; Claims Register claim 8. Claim survives and sharpens. | F9: MEDIUM
A10: 6 | B10: Waiting period options are 30/60/90/180/365 days. | C10: Date of hire is also an option; the period runs to the first day of the month FOLLOWING; it may be waived at initial group enrolment; and it can only be changed at renewal, within 30 days of the anniversary. | D10: Program Guidelines; Employer Admin Guide, Change in Group Policy | E10: Rule R-01. v7 transcript C-0001 states the mechanic imprecisely. | F10: MEDIUM
A11: 7 | B11: Vision and chiropractic can be enrolled without dental. (Flagged as a conflict in v2.) | C11: Resolved against us. Employers are required to offer dental to enrol with ChoiceBuilder, and must offer one PPO carrier alongside the DeltaCare DHMO. Dental is the mandatory anchor line. | D11: Underwriting Guidelines (groups beginning 1/1/2024) | E11: Rule P-32 changes from CONFLICT to a VERIFIED rule with the opposite meaning. Any vision-only group scenario is invalid. | F11: HIGH
A12: 8 | B12: We assumed employer-side COBRA handling was unknown and needed asking. | C12: Fully published. Federal COBRA applies at 20+ employees and notification is solely the employer's responsibility, satisfied if the former member is notified within 14 days of the last day of coverage. Cal-COBRA applies at 2–19 employees and the notification duty sits with the health plans, who have contracted ChoiceBuilder to do it. Cal-COBRA runs to 36 months. Domestic partners are not qualified beneficiaries under federal COBRA but have full election rights under Cal-COBRA. | D12: Employer Admin Guide, About COBRA / About Cal-COBRA | E12: Open question 3 closed. Enables a whole family of compliance-relevant scenarios that were previously off limits. | F12: HIGH
A15: STILL OPEN — needs CHOICE
A16: # | B16: Question | C16: Why it matters | D16: Ask
A17: 1 | B17: What is the guaranteed issue amount on the ChoiceBuilder life plans? | C17: The rule is established — underwriting arises only where the employer requests above guaranteed issue. Only the number is missing, and it decides whether an employer scenario is realistic. | D17: Rebekah
A18: 2 | B18: What proportion of members sit on each dental and vision carrier? | C18: The corpus currently splits carriers by guess. Getting this wrong skews every product-line insight, and it is the one number that cannot be derived from anything public. | D18: Rebekah
A19: 3 | B19: Does monthly full-roster reconciliation exist, and at what group size? | C19: Two transcripts offer it as the remedy to the most common billing complaint in the corpus. The Administrative Guide describes only per-employee forms. If it does not exist, both calls are giving an employer a solution that is not available. | D19: Rebekah
A22: SOURCE DOCUMENTS — all publicly accessible
A23: Ref | B23: Document | C23: Publisher | D23: Version | E23: What it covers | F23: Where
A24: S1 | B24: ChoiceBuilder Employer Administrative Guide (CB.0230) | C24: CHOICE Administrators | D24: 7.20, eff. 12.1.20 | E24: The most complete single source. Eligibility conditions, new hires, military leave, rehires, late enrolees, terminations, family coverage, dependent rules, mid-year changes, group change matrix, COBRA and Cal-COBRA, HIPAA, premium statements, billing, grace periods, renewal timeline, carrier contacts, FAQs. | F24: wordandbrown.com — CB-0230-Employer-Admin-Guide
A25: S2 | B25: ChoiceBuilder Program Guidelines (CB.QPG_3.23) | C25: Choice Builder Insurance Services | D25: eff. 1.7.23 | E25: Group eligibility, available plans by size, effective dates, waiting periods, contribution, participation minimums by line, orthodontia availability, administration fees, six-step selection. | F25: rbgcal.com
A26: S3 | B26: ChoiceBuilder Underwriting Guidelines | C26: CHOICE Administrators | D26: groups beginning 1.1.24, upd. May 2024 | E26: Dental mandatory; takeover credit rules; leasing company treatment; owner/partner eligibility; service area; husband-and-wife waiver treatment; dependent age limit. | F26: dickerson-group.com
A27: S4 | B27: ChoiceBuilder Employer Application (CB 0210A) | C27: CHOICE Administrators | D27: 9/2024, eff. 1.1.25 | E27: Termination on notice, premium due dates, right to non-renew on participation change, ortho takeover credit by carrier, waiver restrictions at 100% contribution. | F27: choicebuilder.com
A28: S5 | B28: ChoiceBuilder Benefit Summary (CB.5234) | C28: CHOICE Administrators | D28: 3.20 eff. 7.1.20 and later | E28: Per-carrier benefit summaries across dental HMO and PPO, vision and chiro. MetLife reimbursement basis, preventive treatment of the annual maximum, VSP additional-pair and laser benefits. | F28: choicebuilder.com
A29: S6 | B29: ChoiceBuilder Employee Enrollment Guide | C29: CHOICE Administrators | D29: 1.24 | E29: Carrier-by-carrier employee-facing summaries; confirms EyeMed is provided by Ameritas and that vision is offered both employer-sponsored and voluntary. | F29: rbgcal.com
A30: S7 | B30: ChoiceBuilder FAQs | C30: CHOICE Administrators | D30: current | E30: Dependent windows, age-out, ID card routing. | F30: choicebuilder.com/FAQs.aspx
A31: S8 | B31: DeltaCare USA Evidence of Coverage | C31: Delta Dental of California | D31: CAEOC-R14 and later | E31: Assigned dentist, specialist referral and preauthorization, emergency and out-of-area rules, copay structure, frequency limits, continuity of care. | F31: Published employer EOCs
A32: S9 | B32: Ameritas dental PPO plan summary | C32: Ameritas via CaliforniaChoice | D32: 2022 onward | E32: 12-month major and ortho waits, comparable-coverage waiver, Dental Rewards, Type 1 treatment of the maximum. | F32: calchoice.com
A33: S10 | B33: Landmark Healthplan material and member notice | C33: Landmark Healthplan of California | D33: current / 2026 | E33: California-only insured plans, no out-of-network payment, direct access, copay and visit ranges, Knox-Keene status. | F33: hr.lhp-ca.com; lhp-ca.com; bopumc.org
A34: S11 | B34: Assurity Group Term Life — Agent Center | C34: Assurity Life Insurance Company | D34: current | E34: Conversion without evidence of insurability, accelerated death benefit terms. | F34: agentcenter.assurity.com
A35: S12 | B35: VSP member and plan material | C35: VSP Vision Care | D35: current | E35: Allowance versus copay, frequency cycles, lens enhancement copays, out-of-network schedule, glasses-or-contacts rule. | F35: vspdirect.com; published VSP plan sheets

Sheet Weekly Volume
A1: Weekly volume plan
A2: Twelve weeks from Monday 6 July to Friday 25 September 2026, ending at today's date so January renewals sit 90 days out and the customer-risk entries are forward-looking rather than historical. Fifty calls a week on average, which makes the platform's default rolling four-week window 200 calls — enough to support most sub-category cuts rather than only the top line. Volume climbs into September as Q4 renewal preparation begins and the Labor Day week is short, because a flat distribution is the first thing that makes a synthetic dataset look synthetic. Calls in the final two weeks have no fourteen-day exposure window and are excluded from the repeat-rate denominator.
A4: Week | B4: Week beginning | C4: Business days | D4: Planned calls | E4: Calls/day | F4: Member | G4: Employer | H4: Note
A5: W1 | B5: Mon 06 Jul 2026 | C5: 5 | D5: 44 | E5: =IFERROR(D5/C5,0) -> 8.8 | F5: =ROUND(D5*'Distribution Targets'!$C$5,0) -> 29 | G5: =D5-F5 -> 15 | H5: Baseline summer volume
A6: W2 | B6: Mon 13 Jul 2026 | C6: 5 | D6: 47 | E6: =IFERROR(D6/C6,0) -> 9.4 | F6: =ROUND(D6*'Distribution Targets'!$C$5,0) -> 31 | G6: =D6-F6 -> 16
A7: W3 | B7: Mon 20 Jul 2026 | C7: 5 | D7: 46 | E7: =IFERROR(D7/C7,0) -> 9.2 | F7: =ROUND(D7*'Distribution Targets'!$C$5,0) -> 30 | G7: =D7-F7 -> 16
A8: W4 | B8: Mon 27 Jul 2026 | C8: 5 | D8: 49 | E8: =IFERROR(D8/C8,0) -> 9.8 | F8: =ROUND(D8*'Distribution Targets'!$C$5,0) -> 32 | G8: =D8-F8 -> 17
A9: W5 | B9: Mon 03 Aug 2026 | C9: 5 | D9: 48 | E9: =IFERROR(D9/C9,0) -> 9.6 | F9: =ROUND(D9*'Distribution Targets'!$C$5,0) -> 31 | G9: =D9-F9 -> 17 | H9: Mid-year enrollment changes begin
A10: W6 | B10: Mon 10 Aug 2026 | C10: 5 | D10: 50 | E10: =IFERROR(D10/C10,0) -> 10 | F10: =ROUND(D10*'Distribution Targets'!$C$5,0) -> 33 | G10: =D10-F10 -> 17
A11: W7 | B11: Mon 17 Aug 2026 | C11: 5 | D11: 52 | E11: =IFERROR(D11/C11,0) -> 10.4 | F11: =ROUND(D11*'Distribution Targets'!$C$5,0) -> 34 | G11: =D11-F11 -> 18
A12: W8 | B12: Mon 24 Aug 2026 | C12: 5 | D12: 53 | E12: =IFERROR(D12/C12,0) -> 10.6 | F12: =ROUND(D12*'Distribution Targets'!$C$5,0) -> 34 | G12: =D12-F12 -> 19
A13: W9 | B13: Mon 31 Aug 2026 | C13: 5 | D13: 50 | E13: =IFERROR(D13/C13,0) -> 10 | F13: =ROUND(D13*'Distribution Targets'!$C$5,0) -> 33 | G13: =D13-F13 -> 17
A14: W10 | B14: Mon 07 Sep 2026 | C14: 4 | D14: 40 | E14: =IFERROR(D14/C14,0) -> 10 | F14: =ROUND(D14*'Distribution Targets'!$C$5,0) -> 26 | G14: =D14-F14 -> 14 | H14: Labor Day — 4 business days
A15: W11 | B15: Mon 14 Sep 2026 | C15: 5 | D15: 60 | E15: =IFERROR(D15/C15,0) -> 12 | F15: =ROUND(D15*'Distribution Targets'!$C$5,0) -> 39 | G15: =D15-F15 -> 21 | H15: Q4 renewal prep; January anniversary groups begin open enrollment
A16: W12 | B16: Mon 21 Sep 2026 | C16: 5 | D16: 61 | E16: =IFERROR(D16/C16,0) -> 12.2 | F16: =ROUND(D16*'Distribution Targets'!$C$5,0) -> 40 | G16: =D16-F16 -> 21 | H16: Corpus closes Fri 25 Sep — no 14-day exposure window; exclude from repeat-rate denominator
A17: TOTAL | C17: =SUM(C5:C16) -> 59 | D17: =SUM(D5:D16) -> 600 | F17: =SUM(F5:F16) -> 392 | G17: =SUM(G5:G16) -> 208
A19: CHECK | B19: =IF(D17=600,"OK — 600 calls","VARIANCE: "&TEXT(D17-600,"+0;-0")) -> OK — 600 calls

Sheet Employer Master
A1: Employer master — 95 groups, sized to the 2–500 band
A2: The spine of the reference dataset, rebuilt so that group size reflects the population ChoiceBuilder actually serves rather than a convenient average. Eligible employees is the field the rules key off: it decides the COBRA regime, the administration fee band, which voluntary dental minimum applies and whether orthodontia is available at all. Enrolled lives are derived from eligible employees and a participation rate that depends on sponsorship, and the threshold column flags every group at or below the requirement that applies to it. Six anchor employers carry 31% of all calls; four of them renew in January, which is what makes the customer-risk entries demonstrable. Complaint rate is per 100 enrolled so dysfunction outranks size, with the raw count always shown beside it. Carrier is now held per line on this sheet rather than spoken in transcripts — ChoiceBuilder
A4: Employer ID | B4: Employer name | C4: Industry | D4: Churn profile | E4: Eligible employees | F4: Enrolled lives | G4: Participation | H4: Fee band | I4: COBRA regime | J4: Region | K4: Renewal month | L4: Broker of record | M4: Dental sponsorship | N4: Lines held | O4: Planned calls | P4: Member calls | Q4: Employer calls | R4: Calls per 100 lives | S4: Annual premium ($) | T4: Threshold status | U4: Tier | V4: Dental carrier | W4: Vision carrier | X4: Life carrier | Y4: Chiro carrier | Z4: Ortho available
A5: EMP-1001 | B5: Cedar Point Workforce Partners | C5: Staffing & Recruitment | D5: High | E5: 420 | F5: 315 | G5: =IFERROR(F5/E5,0) -> 0.75 | H5: =IF(E5<=8,"$25",IF(E5<=20,"$30",IF(E5<=199,"$35","$50"))) -> $50 | I5: =IF(E5<=19,"Cal-COBRA","Federal COBRA") -> Federal COBRA | J5: Orange County | K5: Jan | L5: BRK-02 | M5: ER | N5: Dental + Vision + Chiro | O5: 36 | P5: 24 | Q5: 12 | R5: =IFERROR(O5/F5*100,0) -> 11.428571 | S5: =F5*'Distribution Targets'!$C$34 -> 153090 | T5: =IF(M5="ER",IF(G5<0.7,"BELOW 70% (P-18)",IF(G5<0.75,"Near 70% threshold","OK")),IF(E5<=9,IF(F5<2,"BELOW 2–9 minimum (P-24)",IF(F5=2,"At 2–9 minimum","OK")),IF(F5<5,"BELOW 10–500 minimum (P-23)",IF(F5<7,"Near 10–500 minimum","OK")))) -> OK | U5: =IF(O5>=28,"A — anchor",IF(O5>=10,"B — heavy",IF(O5>=4,"C — moderate","D — tail"))) -> A — anchor | V5: Anthem Blue Cross | W5: EyeMed (via Ameritas) | X5: — | Y5: Landmark Healthplan | Z5: Yes
A6: EMP-1002 | B6: Bellwether Restaurant Group | C6: Hospitality & Food Service | D6: High | E6: 310 | F6: 108 | G6: =IFERROR(F6/E6,0) -> 0.3483871 | H6: =IF(E6<=8,"$25",IF(E6<=20,"$30",IF(E6<=199,"$35","$50"))) -> $50 | I6: =IF(E6<=19,"Cal-COBRA","Federal COBRA") -> Federal COBRA | J6: Los Angeles | K6: Jan | L6: BRK-02 | M6: VOL | N6: Dental + Vision + Chiro | O6: 34 | P6: 23 | Q6: 11 | R6: =IFERROR(O6/F6*100,0) -> 31.481481 | S6: =F6*'Distribution Targets'!$C$34 -> 52488 | T6: =IF(M6="ER",IF(G6<0.7,"BELOW 70% (P-18)",IF(G6<0.75,"Near 70% threshold","OK")),IF(E6<=9,IF(F6<2,"BELOW 2–9 minimum (P-24)",IF(F6=2,"At 2–9 minimum","OK")),IF(F6<5,"BELOW 10–500 minimum (P-23)",IF(F6<7,"Near 10–500 minimum","OK")))) -> OK | U6: =IF(O6>=28,"A — anchor",IF(O6>=10,"B — heavy",IF(O6>=4,"C — moderate","D — tail"))) -> A — anchor | V6: Ameritas PPO | W6: VSP | X6: — | Y6: Landmark Healthplan | Z6: Yes
A7: EMP-1003 | B7: Meridian Industries | C7: Manufacturing | D7: Medium | E7: 240 | F7: 163 | G7: =IFERROR(F7/E7,0) -> 0.67916667 | H7: =IF(E7<=8,"$25",IF(E7<=20,"$30",IF(E7<=199,"$35","$50"))) -> $50 | I7: =IF(E7<=19,"Cal-COBRA","Federal COBRA") -> Federal COBRA | J7: San Diego | K7: Mar | L7: BRK-09 | M7: ER | N7: Dental + Vision | O7: 31 | P7: 21 | Q7: 10 | R7: =IFERROR(O7/F7*100,0) -> 19.018405 | S7: =F7*'Distribution Targets'!$C$34 -> 79218 | T7: =IF(M7="ER",IF(G7<0.7,"BELOW 70% (P-18)",IF(G7<0.75,"Near 70% threshold","OK")),IF(E7<=9,IF(F7<2,"BELOW 2–9 minimum (P-24)",IF(F7=2,"At 2–9 minimum","OK")),IF(F7<5,"BELOW 10–500 minimum (P-23)",IF(F7<7,"Near 10–500 minimum","OK")))) -> BELOW 70% (P-18) | U7: =IF(O7>=28,"A — anchor",IF(O7>=10,"B — heavy",IF(O7>=4,"C — moderate","D — tail"))) -> A — anchor | V7: MetLife PPO | W7: VSP | X7: — | Y7: — | Z7: Yes
A8: EMP-1004 | B8: Drummond Associates | C8: Professional Services | D8: Low | E8: 180 | F8: 86 | G8: =IFERROR(F8/E8,0) -> 0.47777778 | H8: =IF(E8<=8,"$25",IF(E8<=20,"$30",IF(E8<=199,"$35","$50"))) -> $35 | I8: =IF(E8<=19,"Cal-COBRA","Federal COBRA") -> Federal COBRA | J8: Inland Empire | K8: Jan | L8: BRK-06 | M8: VOL | N8: Dental + Vision | O8: 30 | P8: 20 | Q8: 10 | R8: =IFERROR(O8/F8*100,0) -> 34.883721 | S8: =F8*'Distribution Targets'!$C$34 -> 41796 | T8: =IF(M8="ER",IF(G8<0.7,"BELOW 70% (P-18)",IF(G8<0.75,"Near 70% threshold","OK")),IF(E8<=9,IF(F8<2,"BELOW 2–9 minimum (P-24)",IF(F8=2,"At 2–9 minimum","OK")),IF(F8<5,"BELOW 10–500 minimum (P-23)",IF(F8<7,"Near 10–500 minimum","OK")))) -> OK | U8: =IF(O8>=28,"A — anchor",IF(O8>=10,"B — heavy",IF(O8>=4,"C — moderate","D — tail"))) -> A — anchor | V8: DeltaCare USA (DHMO) + Delta Dental PPO | W8: VSP | X8: — | Y8: — | Z8: Yes
A9: EMP-1005 | B9: Fontaine Dental Partners | C9: Healthcare Services | D9: Medium | E9: 95 | F9: 89 | G9: =IFERROR(F9/E9,0) -> 0.93684211 | H9: =IF(E9<=8,"$25",IF(E9<=20,"$30",IF(E9<=199,"$35","$50"))) -> $35 | I9: =IF(E9<=19,"Cal-COBRA","Federal COBRA") -> Federal COBRA | J9: Central Valley | K9: Feb | L9: BRK-01 | M9: ER | N9: Dental + Vision + Chiro | O9: 29 | P9: 19 | Q9: 10 | R9: =IFERROR(O9/F9*100,0) -> 32.58427 | S9: =F9*'Distribution Targets'!$C$34 -> 43254 | T9: =IF(M9="ER",IF(G9<0.7,"BELOW 70% (P-18)",IF(G9<0.75,"Near 70% threshold","OK")),IF(E9<=9,IF(F9<2,"BELOW 2–9 minimum (P-24)",IF(F9=2,"At 2–9 minimum","OK")),IF(F9<5,"BELOW 10–500 minimum (P-23)",IF(F9<7,"Near 10–500 minimum","OK")))) -> OK | U9: =IF(O9>=28,"A — anchor",IF(O9>=10,"B — heavy",IF(O9>=4,"C — moderate","D — tail"))) -> A — anchor | V9: DeltaCare USA (DHMO) + Delta Dental PPO | W9: EyeMed (via Ameritas) | X9: — | Y9: Landmark Healthplan | Z9: Yes
A10: EMP-1006 | B10: Park Mechanical | C10: Construction & Trades | D10: High | E10: 120 | F10: 42 | G10: =IFERROR(F10/E10,0) -> 0.35 | H10: =IF(E10<=8,"$25",IF(E10<=20,"$30",IF(E10<=199,"$35","$50"))) -> $35 | I10: =IF(E10<=19,"Cal-COBRA","Federal COBRA") -> Federal COBRA | J10: Bay Area | K10: Jan | L10: BRK-03 | M10: VOL | N10: Dental | O10: 28 | P10: 19 | Q10: 9 | R10: =IFERROR(O10/F10*100,0) -> 66.666667 | S10: =F10*'Distribution Targets'!$C$34 -> 20412 | T10: =IF(M10="ER",IF(G10<0.7,"BELOW 70% (P-18)",IF(G10<0.75,"Near 70% threshold","OK")),IF(E10<=9,IF(F10<2,"BELOW 2–9 minimum (P-24)",IF(F10=2,"At 2–9 minimum","OK")),IF(F10<5,"BELOW 10–500 minimum (P-23)",IF(F10<7,"Near 10–500 minimum","OK")))) -> OK | U10: =IF(O10>=28,"A — anchor",IF(O10>=10,"B — heavy",IF(O10>=4,"C — moderate","D — tail"))) -> A — anchor | V10: MetLife PPO | W10: — | X10: — | Y10: — | Z10: Yes
A11: EMP-1007 | B11: Vasquez Transport | C11: Logistics & Transport | D11: Medium | E11: 280 | F11: 263 | G11: =IFERROR(F11/E11,0) -> 0.93928571 | H11: =IF(E11<=8,"$25",IF(E11<=20,"$30",IF(E11<=199,"$35","$50"))) -> $50 | I11: =IF(E11<=19,"Cal-COBRA","Federal COBRA") -> Federal COBRA | J11: Orange County | K11: Jan | L11: BRK-02 | M11: ER | N11: Dental + Life | O11: 16 | P11: 10 | Q11: 6 | R11: =IFERROR(O11/F11*100,0) -> 6.0836502 | S11: =F11*'Distribution Targets'!$C$34 -> 127818 | T11: =IF(M11="ER",IF(G11<0.7,"BELOW 70% (P-18)",IF(G11<0.75,"Near 70% threshold","OK")),IF(E11<=9,IF(F11<2,"BELOW 2–9 minimum (P-24)",IF(F11=2,"At 2–9 minimum","OK")),IF(F11<5,"BELOW 10–500 minimum (P-23)",IF(F11<7,"Near 10–500 minimum","OK")))) -> OK | U11: =IF(O11>=28,"A — anchor",IF(O11>=10,"B — heavy",IF(O11>=4,"C — moderate","D — tail"))) -> B — heavy | V11: Delta Dental PPO | W11: — | X11: MetLife | Y11: — | Z11: Yes
A12: EMP-1008 | B12: Cornerstone Associates | C12: Professional Services | D12: Low | E12: 210 | F12: 126 | G12: =IFERROR(F12/E12,0) -> 0.6 | H12: =IF(E12<=8,"$25",IF(E12<=20,"$30",IF(E12<=199,"$35","$50"))) -> $50 | I12: =IF(E12<=19,"Cal-COBRA","Federal COBRA") -> Federal COBRA | J12: Los Angeles | K12: Apr | L12: BRK-03 | M12: VOL | N12: Dental + Vision | O12: 15 | P12: 9 | Q12: 6 | R12: =IFERROR(O12/F12*100,0) -> 11.904762 | S12: =F12*'Distribution Targets'!$C$34 -> 61236 | T12: =IF(M12="ER",IF(G12<0.7,"BELOW 70% (P-18)",IF(G12<0.75,"Near 70% threshold","OK")),IF(E12<=9,IF(F12<2,"BELOW 2–9 minimum (P-24)",IF(F12=2,"At 2–9 minimum","OK")),IF(F12<5,"BELOW 10–500 minimum (P-23)",IF(F12<7,"Near 10–500 minimum","OK")))) -> OK | U12: =IF(O12>=28,"A — anchor",IF(O12>=10,"B — heavy",IF(O12>=4,"C — moderate","D — tail"))) -> B — heavy | V12: Anthem Blue Cross | W12: VSP | X12: — | Y12: — | Z12: No
A13: EMP-1009 | B13: Harborview Technologies | C13: Technology | D13: Low | E13: 165 | F13: 112 | G13: =IFERROR(F13/E13,0) -> 0.67878788 | H13: =IF(E13<=8,"$25",IF(E13<=20,"$30",IF(E13<=199,"$35","$50"))) -> $35 | I13: =IF(E13<=19,"Cal-COBRA","Federal COBRA") -> Federal COBRA | J13: San Diego | K13: Jan | L13: BRK-01 | M13: ER | N13: Dental | O13: 15 | P13: 9 | Q13: 6 | R13: =IFERROR(O13/F13*100,0) -> 13.392857 | S13: =F13*'Distribution Targets'!$C$34 -> 54432 | T13: =IF(M13="ER",IF(G13<0.7,"BELOW 70% (P-18)",IF(G13<0.75,"Near 70% threshold","OK")),IF(E13<=9,IF(F13<2,"BELOW 2–9 minimum (P-24)",IF(F13=2,"At 2–9 minimum","OK")),IF(F13<5,"BELOW 10–500 minimum (P-23)",IF(F13<7,"Near 10–500 minimum","OK")))) -> BELOW 70% (P-18) | U13: =IF(O13>=28,"A — anchor",IF(O13>=10,"B — heavy",IF(O13>=4,"C — moderate","D — tail"))) -> B — heavy | V13: Anthem Blue Cross | W13: — | X13: — | Y13: — | Z13: Yes
A14: EMP-1010 | B14: Alderbrook Workforce Partners | C14: Staffing & Recruitment | D14: High | E14: 150 | F14: 90 | G14: =IFERROR(F14/E14,0) -> 0.6 | H14: =IF(E14<=8,"$25",IF(E14<=20,"$30",IF(E14<=199,"$35","$50"))) -> $35 | I14: =IF(E14<=19,"Cal-COBRA","Federal COBRA") -> Federal COBRA | J14: Inland Empire | K14: May | L14: BRK-06 | M14: VOL | N14: Dental + Vision | O14: 14 | P14: 10 | Q14: 4 | R14: =IFERROR(O14/F14*100,0) -> 15.555556 | S14: =F14*'Distribution Targets'!$C$34 -> 43740 | T14: =IF(M14="ER",IF(G14<0.7,"BELOW 70% (P-18)",IF(G14<0.75,"Near 70% threshold","OK")),IF(E14<=9,IF(F14<2,"BELOW 2–9 minimum (P-24)",IF(F14=2,"At 2–9 minimum","OK")),IF(F14<5,"BELOW 10–500 minimum (P-23)",IF(F14<7,"Near 10–500 minimum","OK")))) -> OK | U14: =IF(O14>=28,"A — anchor",IF(O14>=10,"B — heavy",IF(O14>=4,"C — moderate","D — tail"))) -> B — heavy | V14: Delta Dental PPO | W14: VSP | X14: — | Y14: — | Z14: Yes
A15: EMP-1011 | B15: Foxglove Restaurant Group | C15: Hospitality & Food Service | D15: High | E15: 130 | F15: 112 | G15: =IFERROR(F15/E15,0) -> 0.86153846 | H15: =IF(E15<=8,"$25",IF(E15<=20,"$30",IF(E15<=199,"$35","$50"))) -> $35 | I15: =IF(E15<=19,"Cal-COBRA","Federal COBRA") -> Federal COBRA | J15: Central Valley | K15: Jun | L15: BRK-09 | M15: ER | N15: Dental + Vision + Life + Chiro | O15: 14 | P15: 10 | Q15: 4 | R15: =IFERROR(O15/F15*100,0) -> 12.5 | S15: =F15*'Distribution Targets'!$C$34 -> 54432 | T15: =IF(M15="ER",IF(G15<0.7,"BELOW 70% (P-18)",IF(G15<0.75,"Near 70% threshold","OK")),IF(E15<=9,IF(F15<2,"BELOW 2–9 minimum (P-24)",IF(F15=2,"At 2–9 minimum","OK")),IF(F15<5,"BELOW 10–500 minimum (P-23)",IF(F15<7,"Near 10–500 minimum","OK")))) -> OK | U15: =IF(O15>=28,"A — anchor",IF(O15>=10,"B — heavy",IF(O15>=4,"C — moderate","D — tail"))) -> B — heavy | V15: Delta Dental PPO | W15: EyeMed (via Ameritas) | X15: MetLife | Y15: Landmark Healthplan | Z15: Yes
A16: EMP-1012 | B16: Rosewood Construction | C16: Construction & Trades | D16: High | E16: 120 | F16: 42 | G16: =IFERROR(F16/E16,0) -> 0.35 | H16: =IF(E16<=8,"$25",IF(E16<=20,"$30",IF(E16<=199,"$35","$50"))) -> $35 | I16: =IF(E16<=19,"Cal-COBRA","Federal COBRA") -> Federal COBRA | J16: Bay Area | K16: Jan | L16: BRK-03 | M16: VOL | N16: Dental + Chiro | O16: 13 | P16: 9 | Q16: 4 | R16: =IFERROR(O16/F16*100,0) -> 30.952381 | S16: =F16*'Distribution Targets'!$C$34 -> 20412 | T16: =IF(M16="ER",IF(G16<0.7,"BELOW 70% (P-18)",IF(G16<0.75,"Near 70% threshold","OK")),IF(E16<=9,IF(F16<2,"BELOW 2–9 minimum (P-24)",IF(F16=2,"At 2–9 minimum","OK")),IF(F16<5,"BELOW 10–500 minimum (P-23)",IF(F16<7,"Near 10–500 minimum","OK")))) -> OK | U16: =IF(O16>=28,"A — anchor",IF(O16>=10,"B — heavy",IF(O16>=4,"C — moderate","D — tail"))) -> B — heavy | V16: Delta Dental PPO | W16: — | X16: — | Y16: Landmark Healthplan | Z16: Yes
... A99: EMP-1095 | B99: Zamora Medical Group | C99: Healthcare Services | D99: Medium | E99: 5 | F99: 3 | G99: =IFERROR(F99/E99,0) -> 0.6 | H99: =IF(E99<=8,"$25",IF(E99<=20,"$30",IF(E99<=199,"$35","$50"))) -> $25 | I99: =IF(E99<=19,"Cal-COBRA","Federal COBRA") -> Cal-COBRA | J99: Central Valley | K99: Feb | L99: BRK-23 | M99: VOL | N99: Dental | O99: 2 | P99: 1 | Q99: 1 | R99: =IFERROR(O99/F99*100,0) -> 66.666667 | S99: =F99*'Distribution Targets'!$C$34 -> 1458 | T99: =IF(M99="ER",IF(G99<0.7,"BELOW 70% (P-18)",IF(G99<0.75,"Near 70% threshold","OK")),IF(E99<=9,IF(F99<2,"BELOW 2–9 minimum (P-24)",IF(F99=2,"At 2–9 minimum","OK")),IF(F99<5,"BELOW 10–500 minimum (P-23)",IF(F99<7,"Near 10–500 minimum","OK")))) -> OK | U99: =IF(O99>=28,"A — anchor",IF(O99>=10,"B — heavy",IF(O99>=4,"C — moderate","D — tail"))) -> D — tail | V99: Anthem Blue Cross | W99: — | X99: — | Y99: — | Z99: No
A100: TOTAL | E100: =SUM(E5:E99) -> 6564 | F100: =SUM(F5:F99) -> 4160 | O100: =SUM(O5:O99) -> 600 | P100: =SUM(P5:P99) -> 390 | Q100: =SUM(Q5:Q99) -> 210 | S100: =SUM(S5:S99) -> 2021760
A102: CHECK | B102: =IF(O100=600,"OK — planned calls sum to 600","VARIANCE: "&TEXT(O100-600,"+0;-0")) -> OK — planned calls sum to 600
A104: GROUP SIZE DISTRIBUTION — why it matters
A105: Band (eligible employees) | B105: Groups | C105: Admin fee | D105: COBRA regime | E105: Voluntary dental minimum | F105: Orthodontia availability
A106: 2–8 | B106: =COUNTIFS($E$5:$E$99,">=2",$E$5:$E$99,"<=8") -> 22 | C106: $25 | D106: Cal-COBRA | E106: Anthem 5 eligible / 2 enrolled; MetLife 2 / 2 | F106: Ameritas at 5+; nothing else
A107: 9–19 | B107: =COUNTIFS($E$5:$E$99,">=9",$E$5:$E$99,"<=19") -> 22 | C107: $30 | D107: Cal-COBRA | E107: Anthem 5 / 2; all other dental 10 eligible / 5 enrolled | F107: Ameritas 5+; Anthem and MetLife at 10+
A108: 20 | B108: =COUNTIF($E$5:$E$99,20) -> 2 | C108: $30 | D108: Federal COBRA | E108: As 10–500 | F108: As 10+
A109: 21–199 | B109: =COUNTIFS($E$5:$E$99,">=21",$E$5:$E$99,"<=199") -> 38 | C109: $35 | D109: Federal COBRA | E109: Anthem 5 / 2; all other dental 10 / 5 | F109: All carriers; Delta voluntary needs 25+ eligible
A110: 200–500 | B110: =COUNTIFS($E$5:$E$99,">=200") -> 11 | C110: $50 | D110: Federal COBRA | E110: As above | F110: All carriers
A111: Total | B111: =SUM(B106:B110) -> 95

Sheet Member Master
A1: Member master
A2: 285 members carrying 390 planned member calls across 95 employers. The broker column is a live lookup rather than stored data, which is the point of the modelling rule: change an employer's broker of record in one place and every member and every historical call re-attributes automatically. Repeat callers are built in deliberately, weighted toward the heavier groups, so the repeat-contact and failure-driven-repeat metrics have real pairs to measure rather than coincidences. Distinct member counts are capped at the group's enrolled lives, so a four-person group cannot have six callers.
A4: Member ID | B4: Member name | C4: Age | D4: Employer ID | E4: Employer name | F4: Broker (inherited) | G4: Primary line | H4: Planned calls | I4: Repeat caller
A5: CB-7700001 | B5: Omar Liu | C5: 52 | D5: EMP-1001 | E5: Cedar Point Workforce Partners | F5: =IFERROR(INDEX('Employer Master'!$L$5:$L$99,MATCH(D5,'Employer Master'!$A$5:$A$99,0)),"") -> BRK-02 | G5: Chiro | H5: 2 | I5: =IF(H5>1,"yes","") -> yes
A6: CB-7700002 | B6: Anouk Wexler | C6: 23 | D6: EMP-1001 | E6: Cedar Point Workforce Partners | F6: =IFERROR(INDEX('Employer Master'!$L$5:$L$99,MATCH(D6,'Employer Master'!$A$5:$A$99,0)),"") -> BRK-02 | G6: Vision | H6: 2 | I6: =IF(H6>1,"yes","") -> yes
A7: CB-7700003 | B7: Oscar Nakamura | C7: 27 | D7: EMP-1001 | E7: Cedar Point Workforce Partners | F7: =IFERROR(INDEX('Employer Master'!$L$5:$L$99,MATCH(D7,'Employer Master'!$A$5:$A$99,0)),"") -> BRK-02 | G7: Dental | H7: 2 | I7: =IF(H7>1,"yes","") -> yes
A8: CB-7700004 | B8: Blythe Arellano | C8: 53 | D8: EMP-1001 | E8: Cedar Point Workforce Partners | F8: =IFERROR(INDEX('Employer Master'!$L$5:$L$99,MATCH(D8,'Employer Master'!$A$5:$A$99,0)),"") -> BRK-02 | G8: Vision | H8: 2 | I8: =IF(H8>1,"yes","") -> yes
A9: CB-7700005 | B9: Grace Ortega | C9: 55 | D9: EMP-1001 | E9: Cedar Point Workforce Partners | F9: =IFERROR(INDEX('Employer Master'!$L$5:$L$99,MATCH(D9,'Employer Master'!$A$5:$A$99,0)),"") -> BRK-02 | G9: Vision | H9: 2 | I9: =IF(H9>1,"yes","") -> yes
A10: CB-7700006 | B10: Liesel Ortega | C10: 57 | D10: EMP-1001 | E10: Cedar Point Workforce Partners | F10: =IFERROR(INDEX('Employer Master'!$L$5:$L$99,MATCH(D10,'Employer Master'!$A$5:$A$99,0)),"") -> BRK-02 | G10: Chiro | H10: 2 | I10: =IF(H10>1,"yes","") -> yes
A11: CB-7700007 | B11: Ingrid Zielinski | C11: 30 | D11: EMP-1001 | E11: Cedar Point Workforce Partners | F11: =IFERROR(INDEX('Employer Master'!$L$5:$L$99,MATCH(D11,'Employer Master'!$A$5:$A$99,0)),"") -> BRK-02 | G11: Dental | H11: 2 | I11: =IF(H11>1,"yes","") -> yes
A12: CB-7700008 | B12: Halina Dragomir | C12: 51 | D12: EMP-1001 | E12: Cedar Point Workforce Partners | F12: =IFERROR(INDEX('Employer Master'!$L$5:$L$99,MATCH(D12,'Employer Master'!$A$5:$A$99,0)),"") -> BRK-02 | G12: Dental | H12: 1 | I12: =IF(H12>1,"yes","")
A13: CB-7700009 | B13: Aurelio Steinberg | C13: 38 | D13: EMP-1001 | E13: Cedar Point Workforce Partners | F13: =IFERROR(INDEX('Employer Master'!$L$5:$L$99,MATCH(D13,'Employer Master'!$A$5:$A$99,0)),"") -> BRK-02 | G13: Chiro | H13: 1 | I13: =IF(H13>1,"yes","")
A14: CB-7700010 | B14: Kirsten Kowalczyk | C14: 37 | D14: EMP-1001 | E14: Cedar Point Workforce Partners | F14: =IFERROR(INDEX('Employer Master'!$L$5:$L$99,MATCH(D14,'Employer Master'!$A$5:$A$99,0)),"") -> BRK-02 | G14: Chiro | H14: 1 | I14: =IF(H14>1,"yes","")
A15: CB-7700011 | B15: Emeka Abernathy | C15: 39 | D15: EMP-1001 | E15: Cedar Point Workforce Partners | F15: =IFERROR(INDEX('Employer Master'!$L$5:$L$99,MATCH(D15,'Employer Master'!$A$5:$A$99,0)),"") -> BRK-02 | G15: Vision | H15: 1 | I15: =IF(H15>1,"yes","")
A16: CB-7700012 | B16: Grace Baptiste | C16: 26 | D16: EMP-1001 | E16: Cedar Point Workforce Partners | F16: =IFERROR(INDEX('Employer Master'!$L$5:$L$99,MATCH(D16,'Employer Master'!$A$5:$A$99,0)),"") -> BRK-02 | G16: Chiro | H16: 1 | I16: =IF(H16>1,"yes","")
... A289: CB-7700285 | B289: Perrine Stavros | C289: 30 | D289: EMP-1095 | E289: Zamora Medical Group | F289: =IFERROR(INDEX('Employer Master'!$L$5:$L$99,MATCH(D289,'Employer Master'!$A$5:$A$99,0)),"") -> BRK-23 | G289: Dental | H289: 1 | I289: =IF(H289>1,"yes","")
A290: TOTAL | B290: =COUNTA(A5:A289)&" distinct members" -> 285 distinct members | H290: =SUM(H5:H289) -> 390
A292: CHECK | B292: =IF(H290=390,"OK — 390 member calls","VARIANCE: "&TEXT(H290-390,"+0;-0")) -> OK — 390 member calls

Sheet Employer Contacts
A1: Employer contacts
A2: 101 contacts carrying 210 planned employer calls. Employer calls come from a person, not a company, and which person matters: the authority field records whether that contact can bind the group, because it decides what an agent may action without a second approval. A payroll administrator asking to change contribution is a different call from a CFO asking the same thing. In the smallest groups the caller is usually the owner or a bookkeeper rather than an HR function, which is realistic and changes the tone and the knowledge level of those calls considerably.
A4: Contact ID | B4: Contact name | C4: Role | D4: Authority | E4: Employer ID | F4: Employer name | G4: Broker (inherited) | H4: Planned calls
A5: CON-101 | B5: Quentin Thibault | C5: Payroll Administrator | D5: cannot bind | E5: EMP-1001 | F5: Cedar Point Workforce Partners | G5: =IFERROR(INDEX('Employer Master'!$L$5:$L$99,MATCH(E5,'Employer Master'!$A$5:$A$99,0)),"") -> BRK-02 | H5: 6
A6: CON-102 | B6: Duncan Raman | C6: Office Manager | D6: cannot bind | E6: EMP-1001 | F6: Cedar Point Workforce Partners | G6: =IFERROR(INDEX('Employer Master'!$L$5:$L$99,MATCH(E6,'Employer Master'!$A$5:$A$99,0)),"") -> BRK-02 | H6: 6
A7: CON-103 | B7: Sunil Quiroga | C7: Payroll Administrator | D7: cannot bind | E7: EMP-1002 | F7: Bellwether Restaurant Group | G7: =IFERROR(INDEX('Employer Master'!$L$5:$L$99,MATCH(E7,'Employer Master'!$A$5:$A$99,0)),"") -> BRK-02 | H7: 6
A8: CON-104 | B8: Sandra Nasser | C8: Controller | D8: can bind | E8: EMP-1002 | F8: Bellwether Restaurant Group | G8: =IFERROR(INDEX('Employer Master'!$L$5:$L$99,MATCH(E8,'Employer Master'!$A$5:$A$99,0)),"") -> BRK-02 | H8: 5
A9: CON-105 | B9: Lorna Sarkisian | C9: Owner | D9: can bind | E9: EMP-1003 | F9: Meridian Industries | G9: =IFERROR(INDEX('Employer Master'!$L$5:$L$99,MATCH(E9,'Employer Master'!$A$5:$A$99,0)),"") -> BRK-09 | H9: 5
A10: CON-106 | B10: Gideon Hollis | C10: HR Manager | D10: can bind | E10: EMP-1003 | F10: Meridian Industries | G10: =IFERROR(INDEX('Employer Master'!$L$5:$L$99,MATCH(E10,'Employer Master'!$A$5:$A$99,0)),"") -> BRK-09 | H10: 5
A11: CON-107 | B11: Quill Lindqvist | C11: HR Coordinator | D11: cannot bind | E11: EMP-1004 | F11: Drummond Associates | G11: =IFERROR(INDEX('Employer Master'!$L$5:$L$99,MATCH(E11,'Employer Master'!$A$5:$A$99,0)),"") -> BRK-06 | H11: 5
A12: CON-108 | B12: Gideon Nkemdi | C12: HR Director | D12: can bind | E12: EMP-1004 | F12: Drummond Associates | G12: =IFERROR(INDEX('Employer Master'!$L$5:$L$99,MATCH(E12,'Employer Master'!$A$5:$A$99,0)),"") -> BRK-06 | H12: 5
A13: CON-109 | B13: Dmitri Jaramillo | C13: Benefits Administrator | D13: cannot bind | E13: EMP-1005 | F13: Fontaine Dental Partners | G13: =IFERROR(INDEX('Employer Master'!$L$5:$L$99,MATCH(E13,'Employer Master'!$A$5:$A$99,0)),"") -> BRK-01 | H13: 5
A14: CON-110 | B14: Aurelio Pryor | C14: Office Manager | D14: cannot bind | E14: EMP-1005 | F14: Fontaine Dental Partners | G14: =IFERROR(INDEX('Employer Master'!$L$5:$L$99,MATCH(E14,'Employer Master'!$A$5:$A$99,0)),"") -> BRK-01 | H14: 5
A15: CON-111 | B15: Sunil Baptiste | C15: Bookkeeper | D15: cannot bind | E15: EMP-1006 | F15: Park Mechanical | G15: =IFERROR(INDEX('Employer Master'!$L$5:$L$99,MATCH(E15,'Employer Master'!$A$5:$A$99,0)),"") -> BRK-03 | H15: 5
A16: CON-112 | B16: Vera Villalobos | C16: HR Manager | D16: can bind | E16: EMP-1006 | F16: Park Mechanical | G16: =IFERROR(INDEX('Employer Master'!$L$5:$L$99,MATCH(E16,'Employer Master'!$A$5:$A$99,0)),"") -> BRK-03 | H16: 4
... A105: CON-201 | B105: Bram Mbeki | C105: Bookkeeper | D105: cannot bind | E105: EMP-1095 | F105: Zamora Medical Group | G105: =IFERROR(INDEX('Employer Master'!$L$5:$L$99,MATCH(E105,'Employer Master'!$A$5:$A$99,0)),"") -> BRK-23 | H105: 1
A106: TOTAL | H106: =SUM(H5:H105) -> 210
A108: CHECK | B108: =IF(H106=210,"OK — 210 employer calls","VARIANCE: "&TEXT(H106-210,"+0;-0")) -> OK — 210 employer calls

Sheet Broker Master
A1: Broker master — 30 agencies
A2: Book size comes from Choice's broker records and never from call counts, and that single decision is what makes the small-broker finding possible: dividing attributed calls by book size surfaces the three-group agency that raw volume can never show. The design is deliberate — the brokers highest by raw count are large-book and unremarkable per group, while the highest by rate have books under six. Two brokers are included as controls with small books and no adverse signal, so that a small book alone does not predict the finding. At 600 calls the three adverse small-book agencies carry ten attributed calls each, which is enough to name them credibly but still not enough to quote a precise multiple.
A4: Broker ID | B4: Broker | C4: Agency | D4: Groups in book | E4: Groups in corpus | F4: Region | G4: Attributed calls | H4: Complaints per group | I4: vs channel median | J4: Signal profile
A5: BRK-01 | B5: Anthony Salerno | C5: Salerno Benefits Group | D5: 3 | E5: =COUNTIF('Employer Master'!$L$5:$L$99,A5) -> 3 | F5: Orange County | G5: 10 | H5: =IFERROR(G5/D5,0) -> 3.3333333 | I5: =IFERROR(H5/MEDIAN($H$5:$H$34),0) -> 32.997199 | J5: Adverse — responsiveness
A6: BRK-02 | B6: Marcus Trent | C6: Trent & Associates | D6: 4 | E6: =COUNTIF('Employer Master'!$L$5:$L$99,A6) -> 4 | F6: Los Angeles | G6: 10 | H6: =IFERROR(G6/D6,0) -> 2.5 | I6: =IFERROR(H6/MEDIAN($H$5:$H$34),0) -> 24.747899 | J6: Adverse — misrepresentation at point of sale
A7: BRK-03 | B7: Denise Whitfield | C7: Whitfield Benefits | D7: 5 | E7: =COUNTIF('Employer Master'!$L$5:$L$99,A7) -> 4 | F7: San Diego | G7: 10 | H7: =IFERROR(G7/D7,0) -> 2 | I7: =IFERROR(H7/MEDIAN($H$5:$H$34),0) -> 19.798319 | J7: Adverse — execution and disclosure
A8: BRK-04 | B8: Rafael Ortega | C8: Ortega Insurance Services | D8: 7 | E8: =COUNTIF('Employer Master'!$L$5:$L$99,A8) -> 3 | F8: Inland Empire | G8: 3 | H8: =IFERROR(G8/D8,0) -> 0.42857143 | I8: =IFERROR(H8/MEDIAN($H$5:$H$34),0) -> 4.242497 | J8: Watch
A9: BRK-05 | B9: Karen Lindqvist | C9: Lindqvist Group | D9: 9 | E9: =COUNTIF('Employer Master'!$L$5:$L$99,A9) -> 4 | F9: Bay Area | G9: 3 | H9: =IFERROR(G9/D9,0) -> 0.33333333 | I9: =IFERROR(H9/MEDIAN($H$5:$H$34),0) -> 3.2997199 | J9: Watch
A10: BRK-06 | B10: Patricia Nunez | C10: Nunez Benefit Advisors | D10: 22 | E10: =COUNTIF('Employer Master'!$L$5:$L$99,A10) -> 5 | F10: Orange County | G10: 5 | H10: =IFERROR(G10/D10,0) -> 0.22727273 | I10: =IFERROR(H10/MEDIAN($H$5:$H$34),0) -> 2.249809 | J10: Positive — clients arrive informed
A11: BRK-07 | B11: Gerald Ohm | C11: Ohm & Partners | D11: 34 | E11: =COUNTIF('Employer Master'!$L$5:$L$99,A11) -> 4 | F11: Los Angeles | G11: 9 | H11: =IFERROR(G11/D11,0) -> 0.26470588 | I11: =IFERROR(H11/MEDIAN($H$5:$H$34),0) -> 2.6203658 | J11: Neutral — high volume, low rate
A12: BRK-08 | B12: Lucia Moreno | C12: Moreno Benefits | D12: 41 | E12: =COUNTIF('Employer Master'!$L$5:$L$99,A12) -> 4 | F12: Central Valley | G12: 11 | H12: =IFERROR(G12/D12,0) -> 0.26829268 | I12: =IFERROR(H12/MEDIAN($H$5:$H$34),0) -> 2.6558721 | J12: Neutral — high volume, low rate
A13: BRK-09 | B13: Stephen Vaught | C13: Vaught Agency | D13: 58 | E13: =COUNTIF('Employer Master'!$L$5:$L$99,A13) -> 5 | F13: Los Angeles | G13: 14 | H13: =IFERROR(G13/D13,0) -> 0.24137931 | I13: =IFERROR(H13/MEDIAN($H$5:$H$34),0) -> 2.3894523 | J13: Neutral — highest raw count, unremarkable rate
A14: BRK-10 | B14: Nadine Frost | C14: Frost Insurance | D14: 67 | E14: =COUNTIF('Employer Master'!$L$5:$L$99,A14) -> 4 | F14: Orange County | G14: 12 | H14: =IFERROR(G14/D14,0) -> 0.17910448 | I14: =IFERROR(H14/MEDIAN($H$5:$H$34),0) -> 1.7729838 | J14: Neutral — second highest raw count, lowest rate
A15: BRK-11 | B15: Omar Haddadi | C15: Haddadi Group | D15: 12 | E15: =COUNTIF('Employer Master'!$L$5:$L$99,A15) -> 3 | F15: San Diego | G15: 1 | H15: =IFERROR(G15/D15,0) -> 0.083333333 | I15: =IFERROR(H15/MEDIAN($H$5:$H$34),0) -> 0.82492997 | J15: Neutral
A16: BRK-12 | B16: Beth Kowalski | C16: Kowalski Benefits | D16: 15 | E16: =COUNTIF('Employer Master'!$L$5:$L$99,A16) -> 3 | F16: Bay Area | G16: 1 | H16: =IFERROR(G16/D16,0) -> 0.066666667 | I16: =IFERROR(H16/MEDIAN($H$5:$H$34),0) -> 0.65994398 | J16: Neutral
... A34: BRK-30 | B34: Teresa Falco | C34: Falco Group | D34: 38 | E34: =COUNTIF('Employer Master'!$L$5:$L$99,A34) -> 4 | F34: Bay Area | G34: 4 | H34: =IFERROR(G34/D34,0) -> 0.10526316 | I34: =IFERROR(H34/MEDIAN($H$5:$H$34),0) -> 1.0420168 | J34: Neutral
A35: TOTAL | D35: =SUM(D5:D34) -> 606 | E35: =SUM(E5:E34) -> 95 | G35: =SUM(G5:G34) -> 117
A37: CHECK | B37: =IF(E35=95,"OK — all 95 employers assigned a broker","VARIANCE: "&TEXT(E35-95,"+0;-0")) -> OK — all 95 employers assigned a broker

Sheet Product & Carrier
A1: Product lines, carriers and contact rate
A2: Lives enrolled are within the 95-group corpus sample, not book-wide, because contact rate must use the same population as the calls — dividing sample calls by book-wide enrolment is the classic denominator error and would be found within minutes. Call share deliberately does not mirror enrolment share, and the gap between them is the insight: life covers roughly one member in twelve and generates about three times the contact rate of dental, which says the line is disproportionately hard to administer rather than that it is popular. Dominant failure modes are cross-referenced to the rule IDs that generate them, so a call reason can always be traced to a published rule.
A4: Product line | B4: Carriers | C4: Lives in sample | D4: Attach rate | E4: Planned calls | F4: Call share | G4: Contact rate /1,000/yr | H4: Index vs dental | I4: Dominant failure modes
A5: Dental | B5: DeltaCare USA (DHMO, CA only); Delta Dental PPO; Ameritas; MetLife | C5: 3661 | D5: =IFERROR(C5/'Employer Master'!$F$100,0) -> 0.88004808 | E5: 270 | F5: =IFERROR(E5/$E$10,0) -> 0.45 | G5: =IFERROR(E5*(52/12)/C5*1000,0) -> 319.58481 | H5: =IFERROR(G5/$G$5,0) -> 1 | I5: Major-service waiting periods (C-12) and takeover credit (P-29); annual maximum and network pricing beyond it (C-16); DHMO assigned dentist and specialist referral (C-01, C-02)
A6: Vision | B6: VSP; EyeMed (provided by Ameritas) | C6: 1489 | D6: =IFERROR(C6/'Employer Master'!$F$100,0) -> 0.35793269 | E6: 132 | F6: =IFERROR(E6/$E$10,0) -> 0.22 | G6: =IFERROR(E6*(52/12)/C6*1000,0) -> 384.15044 | H6: =IFERROR(G6/$G$5,0) -> 1.2020297 | I6: Allowance mistaken for copay (C-22); lens enhancement copays (C-23); glasses-or-contacts in a period (C-24)
A7: Life | B7: Assurity; MetLife | C7: 354 | D7: =IFERROR(C7/'Employer Master'!$F$100,0) -> 0.085096154 | E7: 78 | F7: =IFERROR(E7/$E$10,0) -> 0.13 | G7: =IFERROR(E7*(52/12)/C7*1000,0) -> 954.80226 | H7: =IFERROR(G7/$G$5,0) -> 2.9876334 | I7: 100% participation and 100% employer-paid (P-21, P-22); conversion window on termination (C-34); employer's duty to notify conversion rights (A-44)
A8: Chiropractic / Acupuncture | B8: Landmark | C8: 300 | D8: =IFERROR(C8/'Employer Master'!$F$100,0) -> 0.072115385 | E8: 53 | F8: =IFERROR(E8/$E$10,0) -> 0.088333333 | G8: =IFERROR(E8*(52/12)/C8*1000,0) -> 765.55556 | H8: =IFERROR(G8/$G$5,0) -> 2.3954691 | I8: California-only insured plans (C-28); no out-of-network payment at all (C-29); annual visit maximum (C-31)
A9: Program-level (no single line) | B9: n/a | C9: 0 | D9: =IFERROR(C9/'Employer Master'!$F$100,0) -> 0 | E9: 67 | F9: =IFERROR(E9/$E$10,0) -> 0.11166667 | G9: =IFERROR(E9*(52/12)/C9*1000,0) -> 0 | H9: =IFERROR(G9/$G$5,0) -> 0 | I9: Billing and credits (A-09, A-27); terminations (A-06, A-07); COBRA and Cal-COBRA (A-33 to A-42); ID card routing (P-31); participation (P-18 to P-26)
A10: TOTAL | C10: =SUM(C5:C9) -> 5804 | E10: =SUM(E5:E9) -> 600
A12: CHECK | B12: =IF(E10=600,"OK — planned calls sum to 600","VARIANCE: "&TEXT(E10-600,"+0;-0")) -> OK — planned calls sum to 600

Sheet Agent Roster
A1: Agent roster — 20 agents
A2: Twenty agents at thirty calls each, which is exactly the minimum needed to quote an agent-level rate. Variance is within-agent rather than fixed by band, and that matters more than it sounds: if every senior agent scores well on every call the distribution looks engineered and the handle-time finding looks too clean to be true. Strong agents carry poor calls here and weak agents carry good ones. Two agents are modelled as trending across the period, one improving and one declining, so agent trend analysis has something real to find.
A4: Agent ID | B4: Agent | C4: Band | D4: Planned calls | E4: Expected mean score | F4: Score variance (±) | G4: Dominant pattern
A5: AGT-01 | B5: Sarah Whitlock | C5: Senior | D5: 32 | E5: 88 | F5: 7 | G5: Strong — consistent
A6: AGT-02 | B6: Carlos Mendez | C6: Senior | D6: 31 | E6: 88 | F6: 7 | G6: Strong — occasional lapse under volume
A7: AGT-03 | B7: Danielle Park | C7: Senior | D7: 31 | E7: 88 | F7: 7 | G7: Strong
A8: AGT-04 | B8: Priya Anand | C8: Senior | D8: 30 | E8: 88 | F8: 7 | G8: Strong — weaker on life and COBRA
A9: AGT-05 | B9: Adaeze Nwosu | C9: Senior | D9: 30 | E9: 88 | F9: 7 | G9: Strong — best on employer administration
A10: AGT-06 | B10: Michael Osei | C10: Mid | D10: 31 | E10: 76 | F10: 11 | G10: Mixed — accurate, low ownership
A11: AGT-07 | B11: Linda Braithwaite | C11: Mid | D11: 31 | E11: 76 | F11: 11 | G11: Mixed — honest, slow to escalate
A12: AGT-08 | B12: Nicole Trang | C12: Mid | D12: 30 | E12: 76 | F12: 11 | G12: Mixed
A13: AGT-09 | B13: James Okonjo | C13: Mid | D13: 30 | E13: 76 | F13: 11 | G13: Mixed — strong on billing, weak on product rules
A14: AGT-10 | B14: Tony Ferraro | C14: Mid | D14: 30 | E14: 76 | F14: 11 | G14: Mixed — circular calls
A15: AGT-11 | B15: Grace Adeyemi | C15: Mid | D15: 30 | E15: 76 | F15: 11 | G15: Mixed — improving across the period
A16: AGT-12 | B16: Hugo Marchetti | C16: Mid | D16: 30 | E16: 76 | F16: 11 | G16: Mixed — strong on carrier rules, weak on billing
... A24: AGT-20 | B24: Otto Lindgren | C24: Developing | D24: 28 | E24: 61 | F24: 14 | G24: Weak — misses escalation triggers
A25: TOTAL | D25: =SUM(D5:D24) -> 600
A27: CHECK | B27: =IF(D25=600,"OK — planned calls sum to 600","VARIANCE: "&TEXT(D25-600,"+0;-0")) -> OK — planned calls sum to 600

Sheet Distribution Targets
A1: Distribution targets
A2: The counts the transcripts must actually hit. Amber cells are the levers; everything else derives from them, and the check row confirms that caller mix, outcomes and archetypes each still sum to 600. Four sections are new or materially enlarged at this sample size: control exceptions now carry three types each above the rate-quotable threshold, escalation is broken out by trigger type with a floor on the top three, knowledge failures carry a minimum on the top rule so the ranked-articles output is defensible, and process gaps appear for the first time. The archetype mix is unchanged and still matters most — competent-but-constrained at 17% is the bucket that was almost entirely missing from earlier corpora and is a large share of real volume.
A4: Section | B4: Target | C4: Share / value | D4: Calls | E4: Supports entry | F4: Note
A5: CALLER MIX | B5: Member-initiated | C5: 0.65 | D5: =ROUND(C5*600,0) -> 390 | E5: all | F5: Members carry product-line, carrier-rule and knowledge-failure signal
B6: Employer-initiated | C6: 0.35 | D6: =ROUND(C6*600,0) -> 210 | E6: 1, 4, 5, 10 | F6: Employer calls run longer and carry the administration layer
A7: OUTCOMES | B7: Resolved | C7: 0.62 | D7: =ROUND(C7*600,0) -> 372 | E7: —
B8: Partially resolved | C8: 0.12 | D8: =ROUND(C8*600,0) -> 72 | E8: — | F8: In the FCR denominator, never the numerator
B9: Escalated | C9: 0.05 | D9: =ROUND(C9*600,0) -> 30 | E9: 6 | F9: 30 calls
B10: Unresolved | C10: 0.21 | D10: =ROUND(C10*600,0) -> 126 | E10: 4, 9 | F10: 126 calls — the denominator of the failure-driven repeat rate
A11: CALL ARCHETYPE | B11: Competent and resolved | C11: 0.48 | D11: =ROUND(C11*600,0) -> 288 | E11: —
B12: Competent but constrained — policy blocks the outcome | C12: 0.17 | D12: =ROUND(C12*600,0) -> 102 | E12: — | F12: Agent does everything right, caller still unhappy
B13: Circular — long, agent keeps checking, lands nowhere | C13: 0.14 | D13: =ROUND(C13*600,0) -> 84 | E13: — | F13: Long AHT and a poor score; stops the AHT/quality inversion looking engineered
B14: Brush-off — short, closed, procedurally correct | C14: 0.13 | D14: =ROUND(C14*600,0) -> 78 | E14: — | F14: A third of poor calls, not all of them
B15: Escalated or handed off correctly | C15: 0.08 | D15: =ROUND(C15*600,0) -> 48 | E15: 6
A16: COMPLIANCE | B16: No recording disclosure | D16: 36 | E16: 14 | F16: 6% — rate-quotable
B17: Detail disclosed before verification | D17: 30 | E17: 14 | F17: 5% — now rate-quotable, was count-only at 360
B18: Required benefit disclosure omitted | D18: 21 | E18: 14 | F18: 3.5% — count and rank only
A19: ESCALATION | B19: Triggered (denominator) | D19: 72 | E19: 6
B20: — handled correctly | D20: 30 | E20: 6
B21: — refused with no alternative | D21: 42 | E21: 6 | F21: 58% refusal rate
B22: — top 3 trigger types, minimum each | D22: 15 | E22: 6 | F22: Trigger types 4–8 are named with counts, never quoted as rates
A23: REPEAT CONTACT | B23: Distinct callers with 2+ calls | D23: 107 | E23: 4
B24: Failure-driven repeats within 14 days | D24: 48 | E24: 4, 9 | F24: 38% of the 126 unresolved calls
A25: KNOWLEDGE | B25: Knowledge failures total | D25: 72 | E25: 16 | F25: 12% of calls
B26: — top rule_id, minimum | D26: 15 | E26: 16 | F26: Top five rules carry ~60% of failures
A27: PROCESS GAPS | B27: process_gap proposals | D27: 54 | E27: 17 | F27: 9% of calls
B28: — top touchpoint, minimum | D28: 12 | E28: 17
A29: BROKER | B29: Calls naming a broker aloud | D29: 117 | E29: 18 | F29: Minimum 12 in every rolling 4-week block
B30: — adverse, small-book (BRK-01/02/03) | D30: 30 | E30: 18 | F30: 10 each — the invisible-broker finding
B31: — positive attribution | D31: 15 | E31: 18
A32: COMMERCIAL | B32: Expansion intent, unrouted | D32: 30 | E32: 10
B33: Market-test or exit language, verbatim | D33: 24 | E33: 11
A34: REFERENCE | B34: Annual premium per enrolled life ($) | C34: 486 | E34: 3 | F34: Lever used by Employer Master
A36: CHECK | B36: =IF(AND(SUM(D5:D6)=600,SUM(D7:D10)=600,SUM(D11:D15)=600),"OK — caller mix, outcomes and archetypes each sum to 600","VARIANCE — check mix rows") -> OK — caller mix, outcomes and archetypes each sum to 600

Sheet Coverage Matrix
A1: Coverage matrix — combinations, not counts
A2: The corpus is not judged on how many calls it has but on which combinations it covers. The most important of those is outcome against fault: the dataset must not teach that unresolved means a bad agent or that resolved means a good call. A call can close well and carry a compliance breach; an agent can handle a call correctly and still leave it unresolved because the dependency is external. Every cell below is counted from the 150 written calls. Empty cells are the brief for the next batch.
A4: Outcome \ fault | B4: Agent correct | C4: Misinformation | D4: Compliance breach | E4: Missed escalation | F4: Over-escalation | G4: Process failure | H4: Row total
A5: RESOLVED | B5: 74 | C5: 6 | D5: 3 | E5: — | F5: — | G5: 4 | H5: 87
A6: PARTIALLY RESOLVED | B6: 20 | C6: 3 | D6: — | E6: — | F6: — | G6: 3 | H6: 26
A7: ESCALATED | B7: 2 | C7: 1 | D7: — | E7: — | F7: 1 | G7: 9 | H7: 13
A8: UNRESOLVED | B8: 10 | C8: 7 | D8: 5 | E8: 5 | F8: — | G8: 3 | H8: 30
A10: Reading it | B10: Red = no coverage, the batch-3 brief. Amber = fewer than 3, enough to name and not to quantify. Every populated cell is a combination the platform must be able to separate.
A12: OTHER DIMENSIONS
A13: Dimension | B13: Written | C13: Target at 600 | D13: Status | E13: What closes it
A14: Acupuncture named (line is Chiropractic/Acupuncture) | B14: 4 | C14: 24 | D14: Closed in this revision — was 0 of 150 | E14: Four calls now name acupuncture explicitly, including the combined visit maximum that catches members out
A15: Multi-intent calls (primary + secondary issues) | B15: 8 | C15: 75 | D15: Open — 5% against a 12% target | E15: Batch 3 needs ~20 more. Real calls carry a life event, an enrolment, a card and a provider refusal at once
A16: Source contradictions (portal/EOB/directory/agent) | B16: 4 | C16: 24 | D16: Partly closed — was broker-vs-Choice only | E16: Now covers portal vs eligibility, EOB vs provider bill, directory vs provider, agent vs agent
A17: Group-level incidents (N employees, one problem) | B17: 13 | C17: 52 | D17: On pace | E17: Keep at roughly one in ten employer calls
A18: Same problem, different root cause | B18: 22 | C18: 88 | D18: Partly — 22 calls across 11 distinct rules | E18: Design the 'claim not paid' family deliberately: waiting period, exclusion, frequency, maximum, out-of-network, coding, documentation, processing error
A19: Carrier variation held in reference data | B19: 95 | C19: 95 | D19: Closed in this revision | E19: Carrier per line now on Employer Master; five dental, two vision, two life carriers, ortho gated by carrier and size
A20: root_cause_owner populated | B20: 150 | C20: 600 | D20: Closed in this revision — was a third of calls with no owner | E20: 44% of contact volume traces to a root cause Choice owns
A21: Repeat-contact journeys of 3+ calls | B21: 2 | C21: 12 | D21: Thin | E21: Batch 3 should carry 4–5 longer member journeys, not just pairs

Sheet Root Cause
A1: Root cause and preventable volume
A2: Every call now carries a root_cause_owner, not only the ones where a complaint was logged. That closes the gap that made the most commercially useful question unanswerable: what share of our contact volume could Choice have prevented. The answer on 150 calls is 44%. Report the three preventability buckets separately — a blended figure invites an argument about the middle one.
A4: Root cause owner | B4: Calls | C4: Share | D4: Preventable by Choice | E4: What it means operationally
A5: MEMBER_MISUNDERSTANDING | B5: 67 | C5: 45% | D5: Partly — communication | E5: The member was not wrong to ring — they were not told. Fixable at a touchpoint, not by the agent.
A6: CHOICE | B6: 64 | C6: 43% | D6: Yes | E6: Our process, our document or our agent. Directly fixable.
A7: BROKER | B7: 8 | C7: 5% | D7: Partly — broker enablement | E7: A broker action or omission. Fixable through broker enablement, not operations.
A8: PROVIDER | B8: 4 | C8: 3% | D8: No | E8: A dentist, optician or practice. Not ours to fix; worth measuring.
A9: CARRIER | B9: 4 | C9: 3% | D9: Partly — carrier management | E9: Network, directory or claims processing. Fixable through carrier management.
A10: SYSTEM | B10: 2 | C10: 1% | D10: Yes | E10: Two systems disagreeing. Fixable and usually invisible until someone rings.
A11: EMPLOYER | B11: 1 | C11: 1% | D11: Partly — employer enablement | E11: An employer action or omission. Fixable through employer enablement.
A13: HEADLINE | B13: 66 of 150 calls (44%) trace to a root cause Choice owns outright. A further 67 (45%) are members who were never told something — preventable at a touchpoint rather than by the agent who took the call.

Sheet Account Risk Design
A1: Account risk design — how calls are concentrated
A2: An account can only be identified as at risk if several calls from that account share a risk factor. That means call allocation has to be deliberately concentrated, not spread evenly across employers — and this sheet is the rule the allocator must follow. Each account below carries a designed risk story: a dominant signal type that recurs across several of its calls, from more than one caller where possible, so the pattern is visible at account level rather than looking like isolated incidents. Six anchor accounts carry 31% of all volume between them. One of them, Cedar Point, is a deliberate control — high volume, low severity — so that call count alone does not predict a flag.
A4: Account | B4: Tier | C4: Calls at 600 | D4: Written so far | E4: Renews | F4: Designed risk story — the signal that must recur | G4: Callers it must come from | H4: Flag or control
A5: Bellwether Restaurant Group | B5: A — anchor | C5: 34 | D5: 9 | E5: Jan | F5: process_breakdown recurring at employer_portal — submissions accepted and never applied, plus repeat contacts from members whose issue was never fixed | G5: 2 contacts + 5 members | H5: FLAG — multi-signal, Jan renewal
A6: Cedar Point Workforce Partners | B6: A — anchor | C6: 36 | D6: 9 | E6: Jan | F6: member_communication_gap only. High volume because it is the largest group in the book, low severity throughout | G6: 2 contacts + 7 members | H6: CONTROL — volume must not predict a flag
A7: Meridian Industries | B7: A — anchor | C7: 31 | D7: 7 | E7: Mar | F7: knowledge_error recurring on the same rule, plus below-threshold participation held in the reference data | G7: 1 contact + 6 members | H7: FLAG — participation + knowledge
A8: Drummond Associates | B8: A — anchor | C8: 30 | D8: 4 | E8: Jan | F8: knowledge_error and member_communication_gap from an unresponsive broker (BRK-06 book), unresolved inside the renewal window | G8: 1 contact + 3 members | H8: FLAG — broker + renewal window
A9: Fontaine Dental Partners | B9: A — anchor | C9: 29 | D9: 4 | E9: Feb | F9: broker_conduct_adverse recurring against BRK-01, plus network_adequacy on the chiro line | G9: 1 contact + 3 members | H9: FLAG — broker pattern
A10: Park Mechanical | B10: A — anchor | C10: 28 | D10: 3 | E10: Jan | F10: billing_defect and escalation_missed, ending in verbatim exit language before the January renewal | G10: 2 contacts + 1 member | H10: FLAG — retention risk
A11: 14 tier-B accounts | B11: B — heavy | C11: 10–16 each | D11: 30 total | E11: various | F11: One recurring signal each, two to three calls apiece. Enough to appear on a watchlist, not enough to lead it | G11: 1–2 callers each | H11: Mixed
A12: 25 tier-C accounts | B12: C — moderate | C12: 4–7 each | D12: — | E12: various | F12: No designed pattern. Isolated calls that must NOT trigger a flag | G12: 1 caller each | H12: Must stay clean
A13: 50 tier-D accounts | B13: D — tail | C13: 2–3 each | D13: — | E13: various | F13: Single or paired calls. The long tail that proves the flag logic discriminates | G13: 1 caller | H13: Must stay clean
A15: ALLOCATION RULE | B15: Assign each call to the account with the largest remaining capacity against its Employer Master planned-call figure, filtered to accounts whose designed risk story matches the call's dominant signal. Do NOT spread evenly across employers — an even distribution makes account-level risk undetectable by construction, which is what happened in batches 1 and 2a before this sheet existed.
A17: CURRENT STATE | B17: 150 of 600 written. 29 accounts have 2 or more calls; 10 carry a repeated signal type. Four anchors now show a coherent pattern (Bellwether 9, Meridian 7, Fontaine 4, Drummond 4). Park Mechanical and Cedar Point are still thin and are the priority for batch 2b.

Sheet Transcript Tracker
A1: Transcript tracker — written to date
A2: One row per transcript written, in call order, with the tags that matter for coverage. This is the register the team works from: it says what exists, what each call exercises, and — read alongside Batch Coverage — what the next batch has to correct. Employer, industry, broker of record and group size are deliberately absent because they join from caller_ref through the Member Master and Employer Contacts sheets; repeating them here would create two versions of the same fact. Append new batches below row 104 and the Batch Coverage formulas pick them up automatically.
A4: Call ID | B4: Date / time | C4: Batch | D4: Caller type | E4: caller_ref | F4: Caller name | G4: Agent | H4: Category | I4: Product line | J4: Rule refs | K4: Touchpoint | L4: Outcome | M4: Score | N4: AHT (s) | O4: Archetype | P4: Complaint | Q4: Signals | R4: Escalation | S4: Control exceptions | T4: Knowledge failure | U4: Intent | V4: Process gap | W4: Broker named | X4: Repeat of | Y4: Root cause owner | Z4: Preventable | AA4: Primary issue | AB4: Secondary issues | AC4: Impact scope
A5: C-0001 | B5: Mon 06 Jul 2026 09:14 | C5: B1 | D5: MEMBER | E5: CB-7700205 | F5: Leon Castellano | G5: AGT-01|Sarah Whitlock | H5: Claims & EOB | I5: dental | J5: C-12, P-14 | K5: denial_letter_eob | L5: RESOLVED | M5: 91 | N5: 380 | O5: Competent and resolved | P5: present|CHOICE | Q5: member_communication_gap|MEDIUM|Member Communications | R5: triggered false | T5: present|C-12|major-service waiting period is a plan feature, separate from the employer's new-hire period | V5: present|denial letter should name the waiting period and the eligibility date|denial_letter_eob|AGENT|UNVALIDATED | Y5: CHOICE | Z5: Yes | AA5: claims & eob | AC5: 1 member
A6: C-0002 | B6: Mon 06 Jul 2026 10:41 | C6: B1 | D6: MEMBER | E6: CB-7700170 | F6: Vidal Castellano | G6: AGT-14|Brad Nolan | H6: Enrollment & ID Cards | I6: dental | J6: P-31 | K6: id_card_mailer | L6: UNRESOLVED | M6: 44 | N6: 245 | O6: Brush-off | P6: present|CHOICE | Q6: process_breakdown|HIGH|Operations; compliance_disclosure_missing|HIGH|Compliance | R6: triggered false | S6: no_recording_disclosure | T6: present|P-31|cards route to the employer for this carrier, not direct to the member | Y6: CHOICE | Z6: Yes | AA6: enrollment & id cards | AC6: 1 member
A7: C-0003 | B7: Mon 06 Jul 2026 13:22 | C7: B1 | D7: EMPLOYER | E7: CON-137 | F7: Sandra Villalobos | G7: AGT-05|Adaeze Nwosu | H7: Billing & Premium | I7: program | J7: A-27, A-45 | K7: invoice_statement | L7: RESOLVED | M7: 88 | N7: 468 | O7: Competent and resolved | P7: absent | R7: triggered false | V7: present|change codes on the statement should be expanded in plain English|invoice_statement|CALLER|UNVALIDATED | Y7: MEMBER_MISUNDERSTANDING | Z7: Partly — communication | AA7: billing & premium | AC7: 1 group
A8: C-0004 | B8: Tue 07 Jul 2026 09:02 | C8: B1 | D8: MEMBER | E8: CB-7700211 | F8: Mateo Nkemdi | G8: AGT-13|Kayla Brennan | H8: Coverage & Benefits | I8: dental | J8: — | K8: — | L8: RESOLVED | M8: 70 | N8: 192 | O8: Competent and resolved | P8: absent | R8: triggered false | Y8: MEMBER_MISUNDERSTANDING | Z8: Partly — communication | AA8: coverage & benefits | AC8: 1 member
A9: C-0005 | B9: Tue 07 Jul 2026 11:30 | C9: B1 | D9: MEMBER | E9: CB-7700035 | F9: Ewan Haverford | G9: AGT-10|Tony Ferraro | H9: Coverage & Benefits | I9: vision | J9: C-22 | K9: agent_conversation | L9: UNRESOLVED | M9: 51 | N9: 722 | O9: Circular | P9: present|CHOICE | Q9: knowledge_error|MEDIUM|Knowledge Management | R9: triggered false | T9: present|C-22|the frame allowance is a budget, not a copay; the member pays the balance above it | Y9: CHOICE | Z9: Yes | AA9: coverage & benefits | AC9: 1 member
A10: C-0006 | B10: Tue 07 Jul 2026 14:55 | C10: B1 | D10: EMPLOYER | E10: CON-139 | F10: Saoirse Venkatesh | G10: AGT-03|Danielle Park | H10: Enrollment & ID Cards | I10: program | J10: A-11, A-20 | K10: employer_portal | L10: PARTIALLY RESOLVED | M10: 82 | N10: 510 | O10: Competent but constrained | P10: absent | Q10: member_communication_gap|MEDIUM|Member Communications | R10: triggered false | Y10: CHOICE | Z10: Yes | AA10: enrollment & id cards | AC10: 1 group
A11: C-0007 | B11: Wed 08 Jul 2026 10:10 | C11: B1 | D11: MEMBER | E11: CB-7700217 | F11: Jonah Nkemdi | G11: AGT-15|Tiffany Rowe | H11: Claims & EOB | I11: dental | J11: — | K11: — | L11: RESOLVED | M11: 56 | N11: 344 | O11: Competent and resolved | P11: absent | Q11: verification_failure|CRITICAL|Compliance | R11: triggered false | S11: disclosure_before_verification | Y11: CHOICE | Z11: Yes | AA11: claims & eob | AC11: 1 member
A12: C-0008 | B12: Wed 08 Jul 2026 13:48 | C12: B1 | D12: EMPLOYER | E12: CON-101 | F12: Quentin Thibault | G12: AGT-02|Carlos Mendez | H12: Billing & Premium | I12: program | J12: A-06, A-07, A-09 | K12: invoice_statement | L12: ESCALATED | M12: 89 | N12: 555 | O12: Escalated or handed off correctly | P12: present|BROKER | Q12: broker_conduct_adverse|HIGH|Broker Relations; billing_defect|HIGH|Operations / Finance; process_breakdown|HIGH|Operations | R12: triggered true|broker_conduct_adverse|requested_by_caller false|handled true | W12: present|BRK-02|ADVERSE | Y12: BROKER | Z12: Partly — broker enablement | AA12: billing & premium | AC12: eleven employees
A13: C-0009 | B13: Thu 09 Jul 2026 08:50 | C13: B1 | D13: MEMBER | E13: CB-7700219 | F13: Osric Raman | G13: AGT-08|Nicole Trang | H13: Provider Network | I13: dental | J13: C-01 | K13: welcome_pack | L13: RESOLVED | M13: 79 | N13: 270 | O13: Competent and resolved | P13: absent | R13: triggered false | Y13: MEMBER_MISUNDERSTANDING | Z13: Partly — communication | AA13: provider network | AC13: 1 member
A14: C-0010 | B14: Thu 09 Jul 2026 15:20 | C14: B1 | D14: MEMBER | E14: CB-7700183 | F14: Grace Ruiz | G14: AGT-16|Ryan Castellano | H14: Claims & EOB | I14: dental | J14: — | K14: agent_conversation | L14: UNRESOLVED | M14: 47 | N14: 365 | O14: Brush-off | P14: present|CHOICE | Q14: escalation_missed|HIGH|Operations | R14: triggered true|caller_request|requested_by_caller true|handled false | Y14: CHOICE | Z14: Yes | AA14: claims & eob | AC14: 1 member
A15: C-0011 | B15: Fri 10 Jul 2026 11:05 | C15: B1 | D15: EMPLOYER | E15: CON-142 | F15: Imani Hobbs | G15: AGT-04|Priya Anand | H15: Enrollment & ID Cards | I15: program | J15: A-33, A-34, A-37 | K15: cobra_notice | L15: RESOLVED | M15: 86 | N15: 442 | O15: Competent and resolved | P15: absent | R15: triggered false | Y15: MEMBER_MISUNDERSTANDING | Z15: Partly — communication | AA15: enrollment & id cards | AC15: 1 group
A16: C-0012 | B16: Mon 13 Jul 2026 09:30 | C16: B1 | D16: MEMBER | E16: CB-7700111 | F16: Ewan Okafor | G16: AGT-06|Michael Osei | H16: Coverage & Benefits | I16: vision | J16: C-21 | K16: agent_conversation | L16: RESOLVED | M16: 74 | N16: 310 | O16: Competent and resolved | P16: absent | R16: triggered false | Y16: MEMBER_MISUNDERSTANDING | Z16: Partly — communication | AA16: coverage & benefits | AC16: 1 member
A17: C-0013 | B17: Mon 13 Jul 2026 12:15 | C17: B1 | D17: EMPLOYER | E17: CON-131 | F17: Caius Villalobos | G17: AGT-17|Deon Marsh | H17: Billing & Premium | I17: program | J17: A-27, A-28 | K17: invoice_statement | L17: UNRESOLVED | M17: 49 | N17: 700 | O17: Circular | P17: present|CHOICE | Q17: process_breakdown|HIGH|Operations | R17: triggered false | T17: present|A-27|statements bill the following month's coverage, not the month just ended | Y17: CHOICE | Z17: Yes | AA17: billing & premium | AC17: 1 group
A18: C-0014 | B18: Tue 14 Jul 2026 10:00 | C18: B1 | D18: MEMBER | E18: CB-7700092 | F18: Rasmus Aziz | G18: AGT-11|Grace Adeyemi | H18: Life & Beneficiary | I18: life | J18: C-37 | K18: agent_conversation | L18: RESOLVED | M18: 81 | N18: 410 | O18: Competent and resolved | P18: absent | R18: triggered false | Y18: MEMBER_MISUNDERSTANDING | Z18: Partly — communication | AA18: life & beneficiary | AC18: 1 member
A19: C-0015 | B19: Tue 14 Jul 2026 14:35 | C19: B1 | D19: MEMBER | E19: CB-7700223 | F19: Xiomara Pryor | G19: AGT-19|Farrah Bhatti | H19: Coverage & Benefits | I19: dental | J19: — | K19: — | L19: RESOLVED | M19: 61 | N19: 258 | O19: Competent and resolved | P19: absent | Q19: verification_failure|CRITICAL|Compliance | R19: triggered false | S19: disclosure_before_verification | Y19: CHOICE | Z19: Yes | AA19: coverage & benefits | AC19: 1 member
A20: C-0016 | B20: Wed 15 Jul 2026 09:45 | C20: B1 | D20: EMPLOYER | E20: CON-144 | F20: Perrine Lemoine | G20: AGT-07|Linda Braithwaite | H20: Billing & Premium | I20: program | J20: P-15, A-22 | K20: renewal_pack | L20: PARTIALLY RESOLVED | M20: 76 | N20: 492 | O20: Competent but constrained | P20: absent | R20: triggered false | Y20: MEMBER_MISUNDERSTANDING | Z20: Partly — communication | AA20: billing & premium | AC20: 1 group
A21: C-0017 | B21: Wed 15 Jul 2026 16:10 | C21: B1 | D21: MEMBER | E21: CB-7700227 | F21: Steven Winters | G21: AGT-20|Otto Lindgren | H21: Coverage & Benefits | I21: dental | J21: — | K21: agent_conversation | L21: UNRESOLVED | M21: 42 | N21: 220 | O21: Brush-off | P21: present|CHOICE | Q21: escalation_missed|HIGH|Operations | R21: triggered true|scheduled_care_at_risk|requested_by_caller true|handled false | Y21: CHOICE | Z21: Yes | AA21: coverage & benefits | AC21: 1 member
A22: C-0018 | B22: Thu 16 Jul 2026 10:25 | C22: B1 | D22: EMPLOYER | E22: CON-146 | F22: Kirsten Kowalczyk | G22: AGT-09|James Okonjo | H22: Enrollment & ID Cards | I22: program | J22: A-01, A-02 | K22: employer_portal | L22: RESOLVED | M22: 84 | N22: 422 | O22: Competent and resolved | P22: absent | R22: triggered false | Y22: MEMBER_MISUNDERSTANDING | Z22: Partly — communication | AA22: enrollment & id cards | AC22: 1 group
A23: C-0019 | B23: Thu 16 Jul 2026 13:55 | C23: B1 | D23: MEMBER | E23: CB-7700118 | F23: Vidal Okonkwo | G23: AGT-12|Hugo Marchetti | H23: Provider Network | I23: chiro | J23: C-30, C-31 | K23: agent_conversation | L23: RESOLVED | M23: 83 | N23: 355 | O23: Competent and resolved | P23: absent | R23: triggered false | Y23: MEMBER_MISUNDERSTANDING | Z23: Partly — communication | AA23: provider network | AC23: 1 member
A24: C-0020 | B24: Fri 17 Jul 2026 09:20 | C24: B1 | D24: MEMBER | E24: CB-7700231 | F24: Nadira Chigozie | G24: AGT-13|Kayla Brennan | H24: Coverage & Benefits | I24: dental | J24: — | K24: — | L24: UNRESOLVED | M24: 53 | N24: 285 | O24: Brush-off | P24: present|PROVIDER | R24: triggered false | Y24: PROVIDER | Z24: No | AA24: coverage & benefits | AC24: 1 member
A25: C-0021 | B25: Fri 17 Jul 2026 15:40 | C25: B1 | D25: EMPLOYER | E25: CON-109 | F25: Dmitri Jaramillo | G25: AGT-01|Sarah Whitlock | H25: Broker Conduct | I25: program | J25: P-21, P-22 | K25: enrolment_meeting | L25: ESCALATED | M25: 90 | N25: 630 | O25: Escalated or handed off correctly | P25: present|BROKER | Q25: broker_conduct_adverse|HIGH|Broker Relations; member_communication_gap|MEDIUM|Member Communications | R25: triggered true|broker_conduct_adverse|requested_by_caller false|handled true | T25: present|P-21|life is employer-sponsored only, 100% participation, 100% employer-paid — there is no employee election | W25: present|BRK-01|ADVERSE | Y25: BROKER | Z25: Partly — broker enablement | AA25: broker conduct | AC25: four employees
A26: C-0022 | B26: Mon 20 Jul 2026 08:55 | C26: B1 | D26: MEMBER | E26: CB-7700232 | F26: Osric Ishikawa | G26: AGT-06|Michael Osei | H26: Claims & EOB | I26: dental | J26: C-16 | K26: denial_letter_eob | L26: RESOLVED | M26: 77 | N26: 330 | O26: Competent and resolved | P26: absent | Q26: member_communication_gap|MEDIUM|Member Communications | R26: triggered false | V26: present|EOB should state that network pricing continues after the maximum is exhausted|denial_letter_eob|AGENT|UNVALIDATED | Y26: CHOICE | Z26: Yes | AA26: claims & eob | AC26: 1 member
A27: C-0023 | B27: Mon 20 Jul 2026 11:50 | C27: B1 | D27: MEMBER | E27: CB-7700233 | F27: Kamal Nasser | G27: AGT-18|Elena Sokoloff | H27: Coverage & Benefits | I27: dental | J27: A-15 | K27: agent_conversation | L27: PARTIALLY RESOLVED | M27: 64 | N27: 375 | O27: Competent but constrained | P27: present|CHOICE | Q27: member_communication_gap|MEDIUM|Member Communications | R27: triggered false | Y27: CHOICE | Z27: Yes | AA27: coverage & benefits | AC27: 1 member
A28: C-0024 | B28: Tue 21 Jul 2026 10:35 | C28: B1 | D28: MEMBER | E28: CB-7700234 | F28: Xiomara Boyd | G28: AGT-08|Nicole Trang | H28: Coverage & Benefits | I28: dental | J28: — | K28: — | L28: RESOLVED | M28: 72 | N28: 295 | O28: Competent and resolved | P28: absent | R28: triggered false | Y28: MEMBER_MISUNDERSTANDING | Z28: Partly — communication | AA28: coverage & benefits | AC28: 1 member
A29: C-0025 | B29: Tue 21 Jul 2026 14:20 | C29: B1 | D29: EMPLOYER | E29: CON-151 | F29: Uma Villalobos | G29: AGT-05|Adaeze Nwosu | H29: Billing & Premium | I29: program | J29: A-05, A-06, A-09 | K29: invoice_statement | L29: RESOLVED | M29: 87 | N29: 545 | O29: Competent and resolved | P29: present|CHOICE | Q29: billing_defect|HIGH|Operations / Finance | R29: triggered false | T29: present|A-05|voluntary withdrawals are never processed retroactively | Y29: CHOICE | Z29: Yes | AA29: billing & premium | AC29: 1 group
A30: C-0026 | B30: Wed 22 Jul 2026 09:15 | C30: B1 | D30: MEMBER | E30: CB-7700131 | F30: Xiomara Stavros | G30: AGT-03|Danielle Park | H30: Provider Network | I30: vision | J30: C-25 | K30: agent_conversation | L30: RESOLVED | M30: 85 | N30: 400 | O30: Competent and resolved | P30: absent | R30: triggered false | Y30: MEMBER_MISUNDERSTANDING | Z30: Partly — communication | AA30: provider network | AC30: 1 member
A31: C-0027 | B31: Wed 22 Jul 2026 13:05 | C31: B1 | D31: MEMBER | E31: CB-7700236 | F31: Denise Raman | G31: AGT-14|Brad Nolan | H31: Claims & EOB | I31: dental | J31: — | K31: agent_conversation | L31: UNRESOLVED | M31: 40 | N31: 205 | O31: Brush-off | P31: present|CHOICE | Q31: compliance_disclosure_missing|HIGH|Compliance | R31: triggered false | S31: no_recording_disclosure | Y31: CHOICE | Z31: Yes | AA31: claims & eob | AC31: 1 member
A32: C-0028 | B32: Thu 23 Jul 2026 10:45 | C32: B1 | D32: EMPLOYER | E32: CON-153 | F32: Quentin Reyes | G32: AGT-02|Carlos Mendez | H32: Enrollment & ID Cards | I32: program | J32: P-30, P-31 | K32: enrolment_form | L32: RESOLVED | M32: 88 | N32: 535 | O32: Competent and resolved | P32: absent | R32: triggered false | Y32: MEMBER_MISUNDERSTANDING | Z32: Partly — communication | AA32: enrollment & id cards | AC32: 1 group
A33: C-0029 | B33: Thu 23 Jul 2026 15:30 | C33: B1 | D33: MEMBER | E33: CB-7700238 | F33: Hollis Okafor | G33: AGT-11|Grace Adeyemi | H33: Coverage & Benefits | I33: dental | J33: — | K33: — | L33: RESOLVED | M33: 80 | N33: 320 | O33: Competent and resolved | P33: absent | R33: triggered false | Y33: MEMBER_MISUNDERSTANDING | Z33: Partly — communication | AA33: coverage & benefits | AC33: 1 member
A34: C-0030 | B34: Fri 24 Jul 2026 09:40 | C34: B1 | D34: EMPLOYER | E34: CON-133 | F34: Omar Fontaine | G34: AGT-17|Deon Marsh | H34: Enrollment & ID Cards | I34: program | J34: A-12, A-13 | K34: employer_portal | L34: UNRESOLVED | M34: 48 | N34: 675 | O34: Circular | P34: present|CHOICE | Q34: process_breakdown|HIGH|Operations | R34: triggered false | Y34: CHOICE | Z34: Yes | AA34: enrollment & id cards | AC34: 1 group
A35: C-0031 | B35: Fri 24 Jul 2026 14:10 | C35: B1 | D35: MEMBER | E35: CB-7700143 | F35: Quentin Winters | G35: AGT-04|Priya Anand | H35: Life & Beneficiary | I35: life | J35: C-34, A-44 | K35: cobra_notice | L35: RESOLVED | M35: 84 | N35: 365 | O35: Competent and resolved | P35: absent | Q35: member_communication_gap|MEDIUM|Member Communications | R35: triggered false | Y35: CHOICE | Z35: Yes | AA35: life & beneficiary | AC35: 1 member
A36: C-0032 | B36: Mon 27 Jul 2026 08:40 | C36: B1 | D36: MEMBER | E36: CB-7700239 | F36: Quincy Ashby | G36: AGT-13|Kayla Brennan | H36: Coverage & Benefits | I36: dental | J36: — | K36: — | L36: RESOLVED | M36: 68 | N36: 290 | O36: Competent and resolved | P36: absent | R36: triggered false | Y36: MEMBER_MISUNDERSTANDING | Z36: Partly — communication | AA36: coverage & benefits | AC36: 1 member
A37: C-0033 | B37: Mon 27 Jul 2026 11:25 | C37: B1 | D37: EMPLOYER | E37: CON-118 | F37: Derek Kowalczyk | G37: AGT-07|Linda Braithwaite | H37: Provider Network | I37: chiro | J37: C-28, C-29 | K37: renewal_pack | L37: PARTIALLY RESOLVED | M37: 75 | N37: 455 | O37: Competent but constrained | P37: present|CHOICE | Q37: network_adequacy|MEDIUM|Product / Network; member_communication_gap|MEDIUM|Member Communications | R37: triggered false | V37: present|census-versus-network check should run at quotation for multi-state groups|renewal_pack|AGENT|UNVALIDATED | Y37: CHOICE | Z37: Yes | AA37: provider network | AC37: nine employees
A38: C-0034 | B38: Tue 28 Jul 2026 09:55 | C38: B1 | D38: MEMBER | E38: CB-7700240 | F38: Dmitri Obi | G38: AGT-09|James Okonjo | H38: Claims & EOB | I38: dental | J38: C-15 | K38: agent_conversation | L38: RESOLVED | M38: 78 | N38: 340 | O38: Competent and resolved | P38: absent | R38: triggered false | Y38: MEMBER_MISUNDERSTANDING | Z38: Partly — communication | AA38: claims & eob | AC38: 1 member
A39: C-0035 | B39: Tue 28 Jul 2026 13:40 | C39: B1 | D39: MEMBER | E39: CB-7700050 | F39: Jerome Arellano | G39: AGT-20|Otto Lindgren | H39: Coverage & Benefits | I39: vision | J39: C-24 | K39: agent_conversation | L39: UNRESOLVED | M39: 45 | N39: 250 | O39: Brush-off | P39: present|CHOICE | Q39: knowledge_error|MEDIUM|Knowledge Management | R39: triggered false | T39: present|C-24|glasses or contacts in a benefit period, not both | Y39: CHOICE | Z39: Yes | AA39: coverage & benefits | AC39: 1 member
A40: C-0036 | B40: Wed 29 Jul 2026 10:05 | C40: B1 | D40: EMPLOYER | E40: CON-157 | F40: Xavier Fraser | G40: AGT-01|Sarah Whitlock | H40: Billing & Premium | I40: program | J40: P-33, A-27 | K40: invoice_statement | L40: RESOLVED | M40: 89 | N40: 570 | O40: Competent and resolved | P40: absent | R40: triggered false | U40: expansion|verbatim, turn 15 | Y40: MEMBER_MISUNDERSTANDING | Z40: Partly — communication | AA40: billing & premium | AC40: eight employees
A41: C-0037 | B41: Wed 29 Jul 2026 15:15 | C41: B1 | D41: MEMBER | E41: CB-7700242 | F41: Fenna Fontaine | G41: AGT-12|Hugo Marchetti | H41: Coverage & Benefits | I41: dental | J41: C-08 | K41: agent_conversation | L41: RESOLVED | M41: 82 | N41: 305 | O41: Competent and resolved | P41: absent | R41: triggered false | Y41: MEMBER_MISUNDERSTANDING | Z41: Partly — communication | AA41: coverage & benefits | AC41: 1 member
A42: C-0038 | B42: Thu 30 Jul 2026 09:20 | C42: B1 | D42: EMPLOYER | E42: CON-159 | F42: Gustavo Petrova | G42: AGT-08|Nicole Trang | H42: Enrollment & ID Cards | I42: program | J42: A-04 | K42: employer_portal | L42: RESOLVED | M42: 80 | N42: 385 | O42: Competent and resolved | P42: absent | R42: triggered false | Y42: MEMBER_MISUNDERSTANDING | Z42: Partly — communication | AA42: enrollment & id cards | AC42: four employees
A43: C-0039 | B43: Thu 30 Jul 2026 14:45 | C43: B1 | D43: MEMBER | E43: CB-7700244 | F43: Petra Nasser | G43: AGT-15|Tiffany Rowe | H43: Coverage & Benefits | I43: dental | J43: P-28 | K43: agent_conversation | L43: UNRESOLVED | M43: 50 | N43: 275 | O43: Brush-off | P43: present|CHOICE | Q43: knowledge_error|MEDIUM|Knowledge Management | R43: triggered false | T43: present|P-28|orthodontia availability is gated by carrier and group size before any waiting period applies | Y43: CHOICE | Z43: Yes | AA43: coverage & benefits | AC43: 1 member
A44: C-0040 | B44: Fri 31 Jul 2026 10:30 | C44: B1 | D44: EMPLOYER | E44: CON-161 | F44: Pascal Ferrara | G44: AGT-05|Adaeze Nwosu | H44: Billing & Premium | I44: program | J44: A-28, A-29 | K44: invoice_statement | L44: ESCALATED | M44: 87 | N44: 620 | O44: Escalated or handed off correctly | P44: present|CHOICE | Q44: billing_defect|HIGH|Operations / Finance; retention_risk|CRITICAL|Account Management | R44: triggered true|authority_limit|requested_by_caller true|handled true | U44: market_test|verbatim, turn 18 | Y44: CHOICE | Z44: Yes | AA44: billing & premium | AC44: 1 group
A45: C-0041 | B45: Fri 31 Jul 2026 15:50 | C45: B1 | D45: MEMBER | E45: CB-7700246 | F45: Idris Okonkwo | G45: AGT-06|Michael Osei | H45: Coverage & Benefits | I45: dental | J45: — | K45: — | L45: RESOLVED | M45: 73 | N45: 235 | O45: Competent and resolved | P45: absent | R45: triggered false | Y45: MEMBER_MISUNDERSTANDING | Z45: Partly — communication | AA45: coverage & benefits | AC45: 1 member
A46: C-0042 | B46: Mon 03 Aug 2026 09:10 | C46: B1 | D46: MEMBER | E46: CB-7700247 | F46: Gustavo Nasser | G46: AGT-03|Danielle Park | H46: Provider Network | I46: dental | J46: C-02, C-05 | K46: welcome_pack | L46: RESOLVED | M46: 86 | N46: 465 | O46: Competent and resolved | P46: absent | R46: triggered false | Y46: MEMBER_MISUNDERSTANDING | Z46: Partly — communication | AA46: provider network | AC46: 1 member
A47: C-0043 | B47: Mon 03 Aug 2026 13:30 | C47: B1 | D47: EMPLOYER | E47: CON-164 | F47: Lena Nakamura | G47: AGT-19|Farrah Bhatti | H47: Billing & Premium | I47: program | J47: A-31 | K47: invoice_statement | L47: RESOLVED | M47: 71 | N47: 315 | O47: Competent and resolved | P47: absent | R47: triggered false | V47: present|employers repeatedly ask for card or ACH payment|invoice_statement|CALLER|UNVALIDATED | Y47: MEMBER_MISUNDERSTANDING | Z47: Partly — communication | AA47: billing & premium | AC47: 1 group
A48: C-0044 | B48: Tue 04 Aug 2026 10:15 | C48: B1 | D48: MEMBER | E48: CB-7700137 | F48: Bianca Thibault | G48: AGT-10|Tony Ferraro | H48: Claims & EOB | I48: vision | J48: — | K48: agent_conversation | L48: PARTIALLY RESOLVED | M48: 69 | N48: 390 | O48: Competent but constrained | P48: present|CARRIER | R48: triggered false | Y48: CARRIER | Z48: Partly — carrier management | AA48: claims & eob | AC48: 1 member
A49: C-0045 | B49: Tue 04 Aug 2026 15:05 | C49: B1 | D49: MEMBER | E49: CB-7700249 | F49: Denise Lindqvist | G49: AGT-13|Kayla Brennan | H49: Coverage & Benefits | I49: dental | J49: — | K49: — | L49: RESOLVED | M49: 66 | N49: 260 | O49: Competent and resolved | P49: absent | R49: triggered false | Y49: MEMBER_MISUNDERSTANDING | Z49: Partly — communication | AA49: coverage & benefits | AC49: 1 member
A50: C-0046 | B50: Wed 05 Aug 2026 09:35 | C50: B1 | D50: EMPLOYER | E50: CON-166 | F50: Dagny Sorensen | G50: AGT-02|Carlos Mendez | H50: Enrollment & ID Cards | I50: program | J50: A-18, P-30 | K50: enrolment_form | L50: RESOLVED | M50: 85 | N50: 485 | O50: Competent and resolved | P50: absent | R50: triggered false | Y50: MEMBER_MISUNDERSTANDING | Z50: Partly — communication | AA50: enrollment & id cards | AC50: 1 group
A51: C-0047 | B51: Wed 05 Aug 2026 14:25 | C51: B1 | D51: MEMBER | E51: CB-7700251 | F51: Pascal Delgado | G51: AGT-11|Grace Adeyemi | H51: Coverage & Benefits | I51: dental | J51: C-10 | K51: denial_letter_eob | L51: RESOLVED | M51: 79 | N51: 350 | O51: Competent and resolved | P51: present|CHOICE | Q51: member_communication_gap|MEDIUM|Member Communications | R51: triggered false | Y51: CHOICE | Z51: Yes | AA51: coverage & benefits | AC51: 1 member
A52: C-0048 | B52: Thu 06 Aug 2026 10:50 | C52: B1 | D52: MEMBER | E52: CB-7700252 | F52: Tobias Achebe | G52: AGT-17|Deon Marsh | H52: Claims & EOB | I52: dental | J52: — | K52: agent_conversation | L52: UNRESOLVED | M52: 46 | N52: 730 | O52: Circular | P52: present|CHOICE | Q52: escalation_missed|HIGH|Operations | R52: triggered true|caller_request|requested_by_caller true|handled false | Y52: CHOICE | Z52: Yes | AA52: claims & eob | AC52: 1 member
A53: C-0049 | B53: Thu 06 Aug 2026 15:40 | C53: B1 | D53: EMPLOYER | E53: CON-169 | F53: Sable Hobbs | G53: AGT-04|Priya Anand | H53: Enrollment & ID Cards | I53: program | J53: A-16, A-17 | K53: cobra_notice | L53: RESOLVED | M53: 83 | N53: 415 | O53: Competent and resolved | P53: absent | R53: triggered false | Y53: MEMBER_MISUNDERSTANDING | Z53: Partly — communication | AA53: enrollment & id cards | AC53: 1 group
A54: C-0050 | B54: Fri 07 Aug 2026 11:20 | C54: B1 | D54: MEMBER | E54: CB-7700254 | F54: Petra Raman | G54: AGT-16|Ryan Castellano | H54: Coverage & Benefits | I54: dental | J54: — | K54: — | L54: UNRESOLVED | M54: 52 | N54: 280 | O54: Brush-off | P54: present|CHOICE | R54: triggered false | Y54: CHOICE | Z54: Yes | AA54: coverage & benefits | AC54: 1 member
A55: C-0051 | B55: Fri 07 Aug 2026 14:15 | C55: B1 | D55: MEMBER | E55: CB-7700170 | F55: Vidal Castellano | G55: AGT-01|Sarah Whitlock | H55: Enrollment & ID Cards | I55: dental | J55: P-31 | K55: id_card_mailer | L55: RESOLVED | M55: 88 | N55: 430 | O55: Competent and resolved | P55: present|CHOICE | Q55: process_breakdown|HIGH|Operations | R55: triggered false | V55: present|card mailer should tell the member the card went to their employer|id_card_mailer|AGENT|UNVALIDATED | X55: C-0002 | 06 Jul | closed unresolved | Y55: CHOICE | Z55: Yes | AA55: enrollment & id cards | AC55: 1 member
A56: C-0052 | B56: Mon 17 Aug 2026 09:05 | C56: B1 | D56: MEMBER | E56: CB-7700255 | F56: Pascal Marchetti | G56: AGT-09|James Okonjo | H56: Coverage & Benefits | I56: dental | J56: — | K56: — | L56: RESOLVED | M56: 76 | N56: 325 | O56: Competent and resolved | P56: absent | R56: triggered false | Y56: MEMBER_MISUNDERSTANDING | Z56: Partly — communication | AA56: coverage & benefits | AC56: 1 member
A57: C-0053 | B57: Mon 17 Aug 2026 13:45 | C57: B1 | D57: MEMBER | E57: CB-7700183 | F57: Grace Ruiz | G57: AGT-08|Nicole Trang | H57: Claims & EOB | I57: dental | J57: — | K57: agent_conversation | L57: ESCALATED | M57: 84 | N57: 375 | O57: Escalated or handed off correctly | P57: present|CHOICE | Q57: process_breakdown|HIGH|Operations; billing_defect|HIGH|Operations / Finance | R57: triggered true|authority_limit|requested_by_caller false|handled true | V57: present|call notes without a case number produce phantom callbacks|agent_conversation|AGENT|UNVALIDATED | X57: C-0010 | 09 Jul | closed unresolved | Y57: CHOICE | Z57: Yes | AA57: claims & eob | AC57: 1 member
A58: C-0054 | B58: Tue 18 Aug 2026 10:20 | C58: B1 | D58: EMPLOYER | E58: CON-133 | F58: Omar Fontaine | G58: AGT-05|Adaeze Nwosu | H58: Enrollment & ID Cards | I58: program | J58: A-12, A-14 | K58: employer_portal | L58: RESOLVED | M58: 86 | N58: 580 | O58: Competent and resolved | P58: present|CHOICE | Q58: process_breakdown|HIGH|Operations | R58: triggered false | V58: present|portal should return applied/not-applied status, not just submitted|employer_portal|AGENT|UNVALIDATED | X58: C-0030 | 24 Jul | closed unresolved | Y58: CHOICE | Z58: Yes | AA58: enrollment & id cards | AC58: 1 group
A59: C-0055 | B59: Tue 18 Aug 2026 15:10 | C59: B1 | D59: MEMBER | E59: CB-7700149 | F59: Terrence Bell | G59: AGT-14|Brad Nolan | H59: Provider Network | I59: vision | J59: — | K59: agent_conversation | L59: UNRESOLVED | M59: 43 | N59: 245 | O59: Brush-off | P59: present|CHOICE | Q59: compliance_disclosure_missing|HIGH|Compliance | R59: triggered false | S59: no_recording_disclosure | Y59: CHOICE | Z59: Yes | AA59: provider network | AC59: 1 member
A60: C-0056 | B60: Wed 19 Aug 2026 09:30 | C60: B1 | D60: EMPLOYER | E60: CON-172 | F60: Bethany Delgado | G60: AGT-03|Danielle Park | H60: Billing & Premium | I60: program | J60: P-18, P-36 | K60: renewal_pack | L60: PARTIALLY RESOLVED | M60: 81 | N60: 500 | O60: Competent but constrained | P60: absent | Q60: retention_risk|CRITICAL|Account Management | R60: triggered false | U60: market_test|verbatim, turn 16 | Y60: CHOICE | Z60: Yes | AA60: billing & premium | AC60: six employees
A61: C-0057 | B61: Wed 19 Aug 2026 14:00 | C61: B1 | D61: MEMBER | E61: CB-7700166 | F61: Quill Nkemdi | G61: AGT-12|Hugo Marchetti | H61: Coverage & Benefits | I61: chiro | J61: C-32 | K61: denial_letter_eob | L61: RESOLVED | M61: 80 | N61: 335 | O61: Competent and resolved | P61: absent | R61: triggered false | Y61: MEMBER_MISUNDERSTANDING | Z61: Partly — communication | AA61: coverage & benefits | AC61: 1 member
A62: C-0058 | B62: Thu 20 Aug 2026 10:40 | C62: B1 | D62: MEMBER | E62: CB-7700035 | F62: Ewan Haverford | G62: AGT-06|Michael Osei | H62: Coverage & Benefits | I62: vision | J62: C-22, C-23 | K62: agent_conversation | L62: RESOLVED | M62: 82 | N62: 405 | O62: Competent and resolved | P62: absent | Q62: knowledge_error|MEDIUM|Knowledge Management | R62: triggered false | X62: C-0005 | 07 Jul | closed unresolved | Y62: CHOICE | Z62: Yes | AA62: coverage & benefits | AC62: 1 member
A63: C-0059 | B63: Thu 20 Aug 2026 15:25 | C63: B1 | D63: EMPLOYER | E63: CON-173 | F63: Terrence Thibault | G63: AGT-07|Linda Braithwaite | H63: Billing & Premium | I63: program | J63: A-22, A-23 | K63: renewal_pack | L63: RESOLVED | M63: 84 | N63: 470 | O63: Competent and resolved | P63: absent | R63: triggered false | Y63: MEMBER_MISUNDERSTANDING | Z63: Partly — communication | AA63: billing & premium | AC63: 1 group
A64: C-0060 | B64: Fri 21 Aug 2026 09:15 | C64: B1 | D64: MEMBER | E64: CB-7700258 | F64: Nadira Dragomir | G64: AGT-13|Kayla Brennan | H64: Coverage & Benefits | I64: dental | J64: — | K64: — | L64: RESOLVED | M64: 67 | N64: 265 | O64: Competent and resolved | P64: absent | R64: triggered false | Y64: MEMBER_MISUNDERSTANDING | Z64: Partly — communication | AA64: coverage & benefits | AC64: 1 member
A65: C-0061 | B65: Fri 21 Aug 2026 13:50 | C65: B1 | D65: EMPLOYER | E65: CON-131 | F65: Caius Villalobos | G65: AGT-10|Tony Ferraro | H65: Billing & Premium | I65: program | J65: A-27, A-28 | K65: invoice_statement | L65: PARTIALLY RESOLVED | M65: 72 | N65: 665 | O65: Competent but constrained | P65: present|CHOICE | Q65: process_breakdown|HIGH|Operations | R65: triggered false | X65: C-0013 | 13 Jul | closed unresolved | Y65: CHOICE | Z65: Yes | AA65: billing & premium | AC65: 1 group
A66: C-0062 | B66: Mon 24 Aug 2026 08:45 | C66: B1 | D66: MEMBER | E66: CB-7700155 | F66: Duncan Cruz | G66: AGT-11|Grace Adeyemi | H66: Life & Beneficiary | I66: life | J66: C-36 | K66: agent_conversation | L66: RESOLVED | M66: 81 | N66: 355 | O66: Competent and resolved | P66: absent | R66: triggered false | Y66: MEMBER_MISUNDERSTANDING | Z66: Partly — communication | AA66: life & beneficiary | AC66: 1 member
A67: C-0063 | B67: Mon 24 Aug 2026 12:30 | C67: B1 | D67: MEMBER | E67: CB-7700259 | F67: Denise Reyes | G67: AGT-19|Farrah Bhatti | H67: Claims & EOB | I67: dental | J67: — | K67: — | L67: RESOLVED | M67: 63 | N67: 370 | O67: Competent and resolved | P67: absent | Q67: verification_failure|CRITICAL|Compliance | R67: triggered false | S67: disclosure_before_verification | Y67: CHOICE | Z67: Yes | AA67: claims & eob | AC67: 1 member
A68: C-0064 | B68: Tue 25 Aug 2026 10:10 | C68: B1 | D68: EMPLOYER | E68: CON-111 | F68: Sunil Baptiste | G68: AGT-02|Carlos Mendez | H68: Broker Conduct | I68: dental | J68: P-23 | K68: enrolment_meeting | L68: RESOLVED | M68: 87 | N68: 525 | O68: Competent and resolved | P68: present|BROKER | Q68: broker_conduct_adverse|HIGH|Broker Relations | R68: triggered false | T68: present|P-23|voluntary dental minimums are headcount-based, not a percentage | W68: present|BRK-03|ADVERSE | Y68: BROKER | Z68: Partly — broker enablement | AA68: broker conduct | AC68: 1 group
A69: C-0065 | B69: Tue 25 Aug 2026 14:40 | C69: B1 | D69: MEMBER | E69: CB-7700260 | F69: Steven Villalobos | G69: AGT-20|Otto Lindgren | H69: Coverage & Benefits | I69: dental | J69: — | K69: agent_conversation | L69: UNRESOLVED | M69: 49 | N69: 295 | O69: Brush-off | P69: present|CHOICE | R69: triggered false | Y69: CHOICE | Z69: Yes | AA69: coverage & benefits | AC69: 1 member
A70: C-0066 | B70: Wed 26 Aug 2026 09:25 | C70: B1 | D70: EMPLOYER | E70: CON-150 | F70: Nina Bonaventura | G70: AGT-04|Priya Anand | H70: Enrollment & ID Cards | I70: program | J70: A-32 | K70: renewal_pack | L70: RESOLVED | M70: 85 | N70: 440 | O70: Competent and resolved | P70: absent | R70: triggered false | U70: expansion|verbatim, turn 14 | Y70: MEMBER_MISUNDERSTANDING | Z70: Partly — communication | AA70: enrollment & id cards | AC70: 1 group
A71: C-0067 | B71: Wed 26 Aug 2026 15:30 | C71: B1 | D71: MEMBER | E71: CB-7700202 | F71: Jolene Hobbs | G71: AGT-15|Tiffany Rowe | H71: Coverage & Benefits | I71: dental | J71: C-12 | K71: agent_conversation | L71: RESOLVED | M71: 59 | N71: 310 | O71: Competent and resolved | P71: present|CHOICE | Q71: knowledge_error|MEDIUM|Knowledge Management | R71: triggered false | T71: present|C-12|the major-service waiting period is waived for groups with comparable prior coverage | Y71: CHOICE | Z71: Yes | AA71: coverage & benefits | AC71: 1 member
A72: C-0068 | B72: Thu 27 Aug 2026 10:55 | C72: B1 | D72: MEMBER | E72: CB-7700202 | F72: Jolene Hobbs | G72: AGT-01|Sarah Whitlock | H72: Coverage & Benefits | I72: dental | J72: C-12, P-29 | K72: agent_conversation | L72: RESOLVED | M72: 90 | N72: 395 | O72: Competent and resolved | P72: present|CHOICE | Q72: knowledge_error|MEDIUM|Knowledge Management; member_communication_gap|MEDIUM|Member Communications | R72: triggered false | V72: present|takeover credit is never mentioned at member level|enrolment_material|AGENT|UNVALIDATED | X72: C-0067 | 26 Aug | closed resolved but incorrectly | Y72: CHOICE | Z72: Yes | AA72: coverage & benefits | AC72: 1 member
A73: C-0069 | B73: Thu 27 Aug 2026 14:15 | C73: B1 | D73: EMPLOYER | E73: CON-115 | F73: Dagny Yamamoto | G73: AGT-05|Adaeze Nwosu | H73: Broker Conduct | I73: program | J73: P-09, A-23 | K73: broker_material | L73: ESCALATED | M73: 88 | N73: 565 | O73: Escalated or handed off correctly | P73: present|BROKER | Q73: broker_conduct_adverse|HIGH|Broker Relations; revenue_opportunity|LOW|Account Management | R73: triggered true|broker_conduct_adverse|requested_by_caller false|handled true | U73: expansion|verbatim, turn 8 | W73: present|BRK-01|ADVERSE | Y73: BROKER | Z73: Partly — broker enablement | AA73: broker conduct | AC73: 1 group
A74: C-0070 | B74: Fri 28 Aug 2026 09:40 | C74: B1 | D74: MEMBER | E74: CB-7700161 | F74: Sunil Quiroga | G74: AGT-13|Kayla Brennan | H74: Coverage & Benefits | I74: vision | J74: — | K74: — | L74: RESOLVED | M74: 70 | N74: 255 | O74: Competent and resolved | P74: absent | R74: triggered false | Y74: MEMBER_MISUNDERSTANDING | Z74: Partly — communication | AA74: coverage & benefits | AC74: 1 member
A75: C-0071 | B75: Fri 28 Aug 2026 13:20 | C75: B1 | D75: MEMBER | E75: CB-7700262 | F75: Vidal Demir | G75: AGT-08|Nicole Trang | H75: Claims & EOB | I75: dental | J75: C-07 | K75: denial_letter_eob | L75: PARTIALLY RESOLVED | M75: 74 | N75: 425 | O75: Competent but constrained | P75: present|PROVIDER | R75: triggered false | Y75: PROVIDER | Z75: No | AA75: claims & eob | AC75: 1 member
A76: C-0072 | B76: Mon 31 Aug 2026 10:05 | C76: B1 | D76: EMPLOYER | E76: CON-179 | F76: Fenna Valdez | G76: AGT-09|James Okonjo | H76: Billing & Premium | I76: program | J76: A-30, A-31 | K76: invoice_statement | L76: RESOLVED | M76: 82 | N76: 380 | O76: Competent and resolved | P76: absent | R76: triggered false | Y76: MEMBER_MISUNDERSTANDING | Z76: Partly — communication | AA76: billing & premium | AC76: 1 group
A77: C-0073 | B77: Mon 31 Aug 2026 14:50 | C77: B1 | D77: MEMBER | E77: CB-7700264 | F77: Zora Pennington | G77: AGT-12|Hugo Marchetti | H77: Coverage & Benefits | I77: dental | J77: C-11 | K77: agent_conversation | L77: RESOLVED | M77: 78 | N77: 330 | O77: Competent and resolved | P77: absent | R77: triggered false | Y77: MEMBER_MISUNDERSTANDING | Z77: Partly — communication | AA77: coverage & benefits | AC77: 1 member
A78: C-0074 | B78: Tue 01 Sep 2026 09:50 | C78: B1 | D78: EMPLOYER | E78: CON-181 | F78: Carmen Liu | G78: AGT-17|Deon Marsh | H78: Enrollment & ID Cards | I78: program | J78: A-22 | K78: employer_portal | L78: UNRESOLVED | M78: 47 | N78: 645 | O78: Circular | P78: present|CHOICE | R78: triggered false | Y78: CHOICE | Z78: Yes | AA78: enrollment & id cards | AC78: 1 group
A79: C-0075 | B79: Tue 01 Sep 2026 15:35 | C79: B1 | D79: MEMBER | E79: CB-7700266 | F79: Wendell Obi | G79: AGT-06|Michael Osei | H79: Coverage & Benefits | I79: dental | J79: — | K79: — | L79: RESOLVED | M79: 79 | N79: 345 | O79: Competent and resolved | P79: absent | R79: triggered false | Y79: MEMBER_MISUNDERSTANDING | Z79: Partly — communication | AA79: coverage & benefits | AC79: 1 member
A80: C-0076 | B80: Wed 02 Sep 2026 09:20 | C80: B1 | D80: MEMBER | E80: CB-7700267 | F80: Saoirse Demir | G80: AGT-03|Danielle Park | H80: Coverage & Benefits | I80: dental | J80: — | K80: — | L80: RESOLVED | M80: 83 | N80: 410 | O80: Competent and resolved | P80: absent | R80: triggered false | Y80: MEMBER_MISUNDERSTANDING | Z80: Partly — communication | AA80: coverage & benefits | AC80: 1 member
A81: C-0077 | B81: Wed 02 Sep 2026 14:05 | C81: B1 | D81: MEMBER | E81: CB-7700268 | F81: Halina Yamamoto | G81: AGT-14|Brad Nolan | H81: Enrollment & ID Cards | I81: dental | J81: — | K81: agent_conversation | L81: UNRESOLVED | M81: 44 | N81: 270 | O81: Brush-off | P81: present|CHOICE | Q81: compliance_disclosure_missing|HIGH|Compliance | R81: triggered false | S81: no_recording_disclosure | Y81: CHOICE | Z81: Yes | AA81: enrollment & id cards | AC81: 1 member
A82: C-0078 | B82: Thu 03 Sep 2026 10:30 | C82: B1 | D82: EMPLOYER | E82: CON-185 | F82: Rosa Ferrara | G82: AGT-02|Carlos Mendez | H82: Enrollment & ID Cards | I82: program | J82: A-33, A-34, A-36 | K82: cobra_notice | L82: RESOLVED | M82: 86 | N82: 520 | O82: Competent and resolved | P82: absent | R82: triggered false | Y82: MEMBER_MISUNDERSTANDING | Z82: Partly — communication | AA82: enrollment & id cards | AC82: 1 group
A83: C-0079 | B83: Thu 03 Sep 2026 15:20 | C83: B1 | D83: MEMBER | E83: CB-7700179 | F83: Cormac Reyes | G83: AGT-11|Grace Adeyemi | H83: Coverage & Benefits | I83: vision | J83: C-26 | K83: agent_conversation | L83: RESOLVED | M83: 77 | N83: 315 | O83: Competent and resolved | P83: absent | R83: triggered false | Y83: MEMBER_MISUNDERSTANDING | Z83: Partly — communication | AA83: coverage & benefits | AC83: 1 member
A84: C-0080 | B84: Fri 04 Sep 2026 09:05 | C84: B1 | D84: EMPLOYER | E84: CON-186 | F84: Duncan Okonjo | G84: AGT-04|Priya Anand | H84: Enrollment & ID Cards | I84: program | J84: A-03 | K84: enrolment_form | L84: RESOLVED | M84: 84 | N84: 435 | O84: Competent and resolved | P84: absent | R84: triggered false | Y84: MEMBER_MISUNDERSTANDING | Z84: Partly — communication | AA84: enrollment & id cards | AC84: 1 group
A85: C-0081 | B85: Tue 08 Sep 2026 10:15 | C85: B1 | D85: MEMBER | E85: CB-7700050 | F85: Jerome Arellano | G85: AGT-16|Ryan Castellano | H85: Coverage & Benefits | I85: vision | J85: C-24 | K85: agent_conversation | L85: UNRESOLVED | M85: 48 | N85: 285 | O85: Brush-off | P85: present|CHOICE | Q85: escalation_missed|HIGH|Operations; knowledge_error|MEDIUM|Knowledge Management | R85: triggered true|caller_request|requested_by_caller true|handled false | X85: C-0035 | 28 Jul | closed unresolved | Y85: CHOICE | Z85: Yes | AA85: coverage & benefits | AC85: 1 member
A86: C-0082 | B86: Tue 08 Sep 2026 14:40 | C86: B1 | D86: MEMBER | E86: CB-7700050 | F86: Jerome Arellano | G86: AGT-01|Sarah Whitlock | H86: Coverage & Benefits | I86: vision | J86: C-24, C-26 | K86: agent_conversation | L86: RESOLVED | M86: 91 | N86: 550 | O86: Competent and resolved | P86: present|CHOICE | Q86: knowledge_error|MEDIUM|Knowledge Management; member_communication_gap|MEDIUM|Member Communications | R86: triggered false | V86: present|benefit screen should show used/remaining by benefit type, not plan entitlement|agent_conversation|AGENT|UNVALIDATED | X86: C-0081 | 08 Sep | closed unresolved | Y86: CHOICE | Z86: Yes | AA86: coverage & benefits | AC86: 1 member
A87: C-0083 | B87: Wed 09 Sep 2026 09:35 | C87: B1 | D87: EMPLOYER | E87: CON-187 | F87: Vera Fairweather | G87: AGT-07|Linda Braithwaite | H87: Enrollment & ID Cards | I87: program | J87: P-30, P-31 | K87: enrolment_form | L87: RESOLVED | M87: 81 | N87: 365 | O87: Competent and resolved | P87: absent | R87: triggered false | Y87: MEMBER_MISUNDERSTANDING | Z87: Partly — communication | AA87: enrollment & id cards | AC87: 1 group
A88: C-0084 | B88: Wed 09 Sep 2026 13:55 | C88: B1 | D88: MEMBER | E88: CB-7700272 | F88: Marek Demir | G88: AGT-15|Tiffany Rowe | H88: Claims & EOB | I88: dental | J88: — | K88: agent_conversation | L88: PARTIALLY RESOLVED | M88: 62 | N88: 340 | O88: Competent but constrained | P88: present|CARRIER | R88: triggered false | Y88: CARRIER | Z88: Partly — carrier management | AA88: claims & eob | AC88: 1 member
A89: C-0085 | B89: Thu 10 Sep 2026 10:45 | C89: B1 | D89: EMPLOYER | E89: CON-189 | F89: Yolanda Wexler | G89: AGT-05|Adaeze Nwosu | H89: Billing & Premium | I89: program | J89: A-06, A-08, A-09 | K89: invoice_statement | L89: RESOLVED | M89: 88 | N89: 495 | O89: Competent and resolved | P89: present|CHOICE | Q89: billing_defect|HIGH|Operations / Finance | R89: triggered false | Y89: CHOICE | Z89: Yes | AA89: billing & premium | AC89: 1 group
A90: C-0086 | B90: Thu 10 Sep 2026 15:10 | C90: B1 | D90: MEMBER | E90: CB-7700274 | F90: Bianca Aziz | G90: AGT-13|Kayla Brennan | H90: Coverage & Benefits | I90: dental | J90: — | K90: — | L90: RESOLVED | M90: 69 | N90: 260 | O90: Competent and resolved | P90: absent | R90: triggered false | Y90: MEMBER_MISUNDERSTANDING | Z90: Partly — communication | AA90: coverage & benefits | AC90: 1 member
A91: C-0087 | B91: Fri 11 Sep 2026 09:25 | C91: B1 | D91: MEMBER | E91: CB-7700275 | F91: Grace MacAllister | G91: AGT-10|Tony Ferraro | H91: Claims & EOB | I91: dental | J91: — | K91: agent_conversation | L91: UNRESOLVED | M91: 50 | N91: 690 | O91: Circular | P91: present|CHOICE | R91: triggered false | Y91: CHOICE | Z91: Yes | AA91: claims & eob | AC91: 1 member
A92: C-0088 | B92: Fri 11 Sep 2026 14:30 | C92: B1 | D92: EMPLOYER | E92: CON-192 | F92: Ingrid Baptiste | G92: AGT-09|James Okonjo | H92: Billing & Premium | I92: program | J92: P-33, A-27 | K92: invoice_statement | L92: RESOLVED | M92: 83 | N92: 460 | O92: Competent and resolved | P92: absent | R92: triggered false | Y92: MEMBER_MISUNDERSTANDING | Z92: Partly — communication | AA92: billing & premium | AC92: eight employees
A93: C-0089 | B93: Mon 14 Sep 2026 08:50 | C93: B1 | D93: MEMBER | E93: CB-7700175 | F93: Nikhil Yamamoto | G93: AGT-12|Hugo Marchetti | H93: Coverage & Benefits | I93: chiro | J93: C-29, C-30 | K93: agent_conversation | L93: RESOLVED | M93: 80 | N93: 325 | O93: Competent and resolved | P93: absent | R93: triggered false | Y93: MEMBER_MISUNDERSTANDING | Z93: Partly — communication | AA93: coverage & benefits | AC93: 1 member
A94: C-0090 | B94: Mon 14 Sep 2026 13:15 | C94: B1 | D94: EMPLOYER | E94: CON-126 | F94: Juno Nkemdi | G94: AGT-08|Nicole Trang | H94: Broker Conduct | I94: program | J94: P-16, P-20 | K94: enrolment_meeting | L94: PARTIALLY RESOLVED | M94: 76 | N94: 415 | O94: Competent but constrained | P94: present|BROKER | Q94: broker_conduct_adverse|HIGH|Broker Relations | R94: triggered false | T94: present|P-16|chiropractic must be 100% employer-paid; there is no voluntary option | W94: present|BRK-02|ADVERSE | Y94: BROKER | Z94: Partly — broker enablement | AA94: broker conduct | AC94: 1 group
A95: C-0091 | B95: Tue 15 Sep 2026 09:40 | C95: B1 | D95: MEMBER | E95: CB-7700277 | F95: Yolanda Okonjo | G95: AGT-19|Farrah Bhatti | H95: Coverage & Benefits | I95: dental | J95: — | K95: — | L95: RESOLVED | M95: 72 | N95: 295 | O95: Competent and resolved | P95: absent | R95: triggered false | Y95: MEMBER_MISUNDERSTANDING | Z95: Partly — communication | AA95: coverage & benefits | AC95: 1 member
A96: C-0092 | B96: Tue 15 Sep 2026 14:20 | C96: B1 | D96: EMPLOYER | E96: CON-114 | F96: Rasmus Nkemdi | G96: AGT-01|Sarah Whitlock | H96: Broker Conduct | I96: program | J96: P-36 | K96: broker_material | L96: ESCALATED | M96: 92 | N96: 605 | O96: Escalated or handed off correctly | P96: present|BROKER | Q96: broker_conduct_adverse|HIGH|Broker Relations; retention_risk|CRITICAL|Account Management | R96: triggered true|contested_document|requested_by_caller false|handled true | U96: market_test|verbatim, turn 20 | W96: present|BRK-03|ADVERSE | Y96: BROKER | Z96: Partly — broker enablement | AA96: broker conduct | AC96: 1 group
A97: C-0093 | B97: Wed 16 Sep 2026 10:00 | C97: B1 | D97: MEMBER | E97: CB-7700193 | F97: Rasmus Bonaventura | G97: AGT-06|Michael Osei | H97: Life & Beneficiary | I97: life | J97: C-35 | K97: agent_conversation | L97: RESOLVED | M97: 78 | N97: 350 | O97: Competent and resolved | P97: absent | R97: triggered false | Y97: MEMBER_MISUNDERSTANDING | Z97: Partly — communication | AA97: life & beneficiary | AC97: 1 member
A98: C-0094 | B98: Wed 16 Sep 2026 15:45 | C98: B1 | D98: MEMBER | E98: CB-7700278 | F98: Aurelio Castellanos | G98: AGT-20|Otto Lindgren | H98: Provider Network | I98: dental | J98: — | K98: agent_conversation | L98: UNRESOLVED | M98: 46 | N98: 250 | O98: Brush-off | P98: present|CHOICE | R98: triggered false | Y98: CHOICE | Z98: Yes | AA98: provider network | AC98: 1 member
A99: C-0095 | B99: Thu 17 Sep 2026 09:30 | C99: B1 | D99: EMPLOYER | E99: CON-195 | F99: Nadira Bonaventura | G99: AGT-03|Danielle Park | H99: Enrollment & ID Cards | I99: program | J99: A-19 | K99: enrolment_form | L99: RESOLVED | M99: 85 | N99: 445 | O99: Competent and resolved | P99: absent | R99: triggered false | Y99: MEMBER_MISUNDERSTANDING | Z99: Partly — communication | AA99: enrollment & id cards | AC99: 1 group
A100: C-0096 | B100: Thu 17 Sep 2026 14:05 | C100: B1 | D100: MEMBER | E100: CB-7700280 | F100: Uma Ferrara | G100: AGT-11|Grace Adeyemi | H100: Coverage & Benefits | I100: dental | J100: C-14 | K100: agent_conversation | L100: RESOLVED | M100: 82 | N100: 375 | O100: Competent and resolved | P100: absent | R100: triggered false | Y100: MEMBER_MISUNDERSTANDING | Z100: Partly — communication | AA100: coverage & benefits | AC100: 1 member
A101: C-0097 | B101: Fri 18 Sep 2026 10:20 | C101: B1 | D101: MEMBER | E101: CB-7700281 | F101: Tamsin Petrova | G101: AGT-13|Kayla Brennan | H101: Coverage & Benefits | I101: dental | J101: — | K101: — | L101: PARTIALLY RESOLVED | M101: 65 | N101: 305 | O101: Competent but constrained | P101: absent | R101: triggered false | Y101: MEMBER_MISUNDERSTANDING | Z101: Partly — communication | AA101: coverage & benefits | AC101: 1 member
...

Sheet Batch Coverage
A1: Batch coverage — written against target
A2: What the corpus has so far against what the design says it needs. Written before anyone asks: batch 1 drifted in four places and this sheet records it rather than hiding it. Competent-and-resolved calls are over-produced and circular calls under-produced, because circular calls are long and slow to write and the easy ones got written first. Vision, life and chiropractic are all behind and program-level employer calls are ahead. Broker-attributed calls are the most serious gap at six against a pro-rata twenty. None of this matters while it is visible and corrected in the next batch; it matters enormously if it is discovered at 600. Batch 2 should be written against the Gap column, not against the design targets.
A4: Section | B4: Measure | C4: Target at 600 | D4: Written (at 600) | E4: Target (600) | F4: Gap | G4: Note
A5: VOLUME | B5: Transcripts written | C5: 600 | D5: 600 | E5: 600 | F5: 0 | G5: Batch 1 of an expected six batches of 100.
A6: CALLER MIX | B6: Member-initiated | C6: 390 | D6: 401 | E6: 390 | F6: 11 | G6: On plan.
B7: Employer-initiated | C7: 210 | D7: 199 | E7: 210 | F7: -11 | G7: On plan.
A8: OUTCOMES | B8: Resolved | C8: 372 | D8: 368 | E8: 372 | F8: -4 | G8: Running ahead. Batch 2 should lean harder on the other three.
B9: Partially resolved | C9: 72 | D9: 73 | E9: 72 | F9: 1 | G9: On plan.
B10: Escalated | C10: 30 | D10: 34 | E10: 30 | F10: 4 | G10: Running ahead; ease off in batch 2.
B11: Unresolved | C11: 126 | D11: 125 | E11: 126 | F11: -1 | G11: Slightly behind. Needed as the repeat-rate denominator.
A12: ARCHETYPE | B12: Competent and resolved | C12: 288 | D12: 348 | E12: 288 | F12: 60 | G12: Well ahead — correct in batch 2.
B13: Competent but constrained | C13: 102 | D13: 84 | E13: 102 | F13: -18 | G13: Behind. The most under-represented archetype.
B14: Circular | C14: 84 | D14: 66 | E14: 84 | F14: -18 | G14: Behind by half. These are long and expensive to write and were under-produced.
B15: Brush-off | C15: 78 | D15: 68 | E15: 78 | F15: -10 | G15: On plan.
B16: Escalated or handed off | C16: 48 | D16: 34 | E16: 48 | F16: -14 | G16: On plan.
A17: PRODUCT | B17: Dental | C17: 270 | D17: 263 | E17: 270 | F17: -7 | G17: On plan.
B18: Vision | C18: 132 | D18: 129 | E18: 132 | F18: -3 | G18: Behind. Batch 2 needs roughly double.
B19: Life | C19: 78 | D19: 73 | E19: 78 | F19: -5 | G19: Behind. The thinnest cell and the one that needs 30+ to quote a rate.
B20: Chiropractic | C20: 53 | D20: 52 | E20: 53 | F20: -1 | G20: Behind.
B21: Program-level | C21: 67 | D21: 83 | E21: 67 | F21: 16 | G21: Well ahead — employer administration calls over-produced.
A22: RULE COVERAGE | B22: Calls anchored to a published rule | C22: ~62% | D22: 69% | E22: ~62% | G22: Deliberate design: members call about things that are not rules.
B23: Calls with no governing rule | C23: ~38% | D23: 31% | E23: ~38% | G23: General service concerns — address changes, provider complaints, out-of-scope questions, broken glasses, language access. These must stay roughly a third or the corpus reads as a rules quiz.
A24: COMPLIANCE | B24: No recording disclosure | C24: 36 | D24: 35 | E24: 36 | F24: -1 | G24: Behind pro-rata (6 expected).
B25: Disclosure before verification | C25: 30 | D25: 28 | E25: 30 | F25: -2 | G25: Behind pro-rata (5 expected).
A26: ESCALATION | B26: Triggered | C26: 72 | D26: 70 | E26: 72 | F26: -2 | G26: Slightly behind.
B27: — handled | C27: 30 | D27: 37 | E27: 30 | F27: 7 | G27: Ahead.
B28: — refused | C28: 42 | D28: 34 | E28: 42 | F28: -8 | G28: Well behind. Batch 2 needs more refused escalations to hold the 58% refusal rate.
A29: KNOWLEDGE | B29: Knowledge failures | C29: 72 | D29: 68 | E29: 72 | F29: -4 | G29: Slightly behind.
A30: PROCESS GAPS | B30: process_gap proposals | C30: 54 | D30: 36 | E30: 54 | F30: -18 | G30: Ahead. New tag, exercised well.
A31: BROKER | B31: Calls naming a broker aloud | C31: 117 | D31: 104 | E31: 117 | F31: -13 | G31: Well behind. Batch 2 must carry roughly 25 to stay on track.
A32: REPEAT CONTACT | B32: Failure-driven repeats | C32: 48 | D32: 45 | E32: 48 | F32: -3 | G32: On plan. Eight repeat pairs written, each following an unresolved call.
A33: COMMERCIAL | B33: Expansion intent | C33: 30 | D33: 23 | E33: 30 | F33: -7 | G33: Behind.
B34: Market-test / exit language | C34: 24 | D34: 18 | E34: 24 | F34: -6 | G34: On plan.
A36: How to use this | B36: Red rows are four or more behind pro-rata and are the batch 2 brief. When batch 2 is written, extend the Transcript Tracker below the last row, change B1 to B2 in the batch column, and recompute this sheet. The design targets in column C do not move.
